{
  "novel_id": "Vạn Cổ Đao_Tuyết Mãn Cung Đao",
  "source_type": "source_full",
  "metadata": {
    "title_vi": "Sơn Trung Khách",
    "author": "Unknown"
  },
  "chapters": [
    {
      "index": 1,
      "file": "Chapter 0001 山中客.md",
      "status": "done",
      "error": "",
      "translated_file": "Chương 0001 Sơn Trung Khách.md",
      "title": "山中客"
    },
    {
      "index": 2,
      "file": "Chapter 0002 红衣映雪，伏虎少侠.md",
      "status": "done",
      "error": "",
      "translated_file": "Chương 0002 Áo đỏ rực rỡ, thiếu hiệp Phục Hổ.md",
      "title": "红衣映雪，伏虎少侠"
    },
    {
      "index": 3,
      "file": "Chapter 0003 刀.md",
      "status": "done",
      "error": "",
      "translated_file": "Chương 0003 Dao.md",
      "title": "刀"
    },
    {
      "index": 4,
      "file": "Chapter 0004 月黑风高.md",
      "status": "done",
      "error": "",
      "translated_file": "Chương 0004 Nguyệt hắc phong cao.md",
      "title": "月黑风高"
    },
    {
      "index": 5,
      "file": "Chapter 0005 杀人夜（上）.md",
      "status": "done",
      "error": "",
      "translated_file": "Chương 0005 Đêm giết người (Thượng).md",
      "title": "杀人夜（上）"
    },
    {
      "index": 6,
      "file": "Chapter 0006 杀人夜（下）.md",
      "status": "done",
      "error": "",
      "translated_file": "Chương 0006 Đêm sát nhân (hạ).md",
      "title": "杀人夜（下）"
    },
    {
      "index": 7,
      "file": "Chapter 0007 同居.md",
      "status": "done",
      "error": "",
      "translated_file": "Chương 0007 Ở chung.md",
      "title": "同居"
    },
    {
      "index": 8,
      "file": "Chapter 0008 无欲则刚.md",
      "status": "pending",
      "title": "无欲则刚"
    },
    {
      "index": 9,
      "file": "Chapter 0009 大雪球子.md",
      "status": "pending",
      "title": "大雪球子"
    },
    {
      "index": 10,
      "file": "Chapter 0010 波澜.md",
      "status": "pending",
      "title": "波澜"
    },
    {
      "index": 11,
      "file": "Chapter 0011 神照.md",
      "status": "pending",
      "title": "神照"
    },
    {
      "index": 12,
      "file": "Chapter 0012 老猿献酒.md",
      "status": "pending",
      "title": "老猿献酒"
    },
    {
      "index": 13,
      "file": "Chapter 0013 我跟它们不熟.md",
      "status": "pending",
      "title": "我跟它们不熟"
    },
    {
      "index": 14,
      "file": "Chapter 0014 雪岭杀机.md",
      "status": "pending",
      "title": "雪岭杀机"
    },
    {
      "index": 15,
      "file": "Chapter 0015 谁是猎物？.md",
      "status": "pending",
      "title": "谁是猎物？"
    },
    {
      "index": 16,
      "file": "Chapter 0016 斩九品.md",
      "status": "pending",
      "title": "斩九品"
    },
    {
      "index": 17,
      "file": "Chapter 0017 铜皮.md",
      "status": "pending",
      "title": "铜皮"
    },
    {
      "index": 18,
      "file": "Chapter 0018 夫君死了（求收藏求追读）.md",
      "status": "pending",
      "title": "夫君死了（求收藏求追读）"
    },
    {
      "index": 19,
      "file": "Chapter 0019 折磨.md",
      "status": "pending",
      "title": "折磨"
    },
    {
      "index": 20,
      "file": "Chapter 0020 拦路.md",
      "status": "pending",
      "title": "拦路"
    },
    {
      "index": 21,
      "file": "Chapter 0021 聘礼（求收藏追读）.md",
      "status": "pending",
      "title": "聘礼（求收藏追读）"
    },
    {
      "index": 22,
      "file": "Chapter 0022 外地亲戚.md",
      "status": "pending",
      "title": "外地亲戚"
    },
    {
      "index": 23,
      "file": "Chapter 0023 武学四境（首盟落叶风飞加更）.md",
      "status": "pending",
      "title": "武学四境（首盟落叶风飞加更）"
    },
    {
      "index": 24,
      "file": "Chapter 0024 恶狼.md",
      "status": "pending",
      "title": "恶狼"
    },
    {
      "index": 25,
      "file": "Chapter 0025 反噬.md",
      "status": "pending",
      "title": "反噬"
    },
    {
      "index": 26,
      "file": "Chapter 0026 女孩和狗.md",
      "status": "pending",
      "title": "女孩和狗"
    },
    {
      "index": 27,
      "file": "Chapter 0027 江湖的意义.md",
      "status": "pending",
      "title": "江湖的意义"
    },
    {
      "index": 28,
      "file": "Chapter 0028 踩点.md",
      "status": "pending",
      "title": "踩点"
    },
    {
      "index": 29,
      "file": "Chapter 0029 借刀杀人.md",
      "status": "pending",
      "title": "借刀杀人"
    },
    {
      "index": 30,
      "file": "Chapter 0030 杀！（求收藏求追读）.md",
      "status": "pending",
      "title": "杀！（求收藏求追读）"
    },
    {
      "index": 31,
      "file": "Chapter 0031 收徒.md",
      "status": "pending",
      "title": "收徒"
    },
    {
      "index": 32,
      "file": "Chapter 0032 知微.md",
      "status": "pending",
      "title": "知微"
    },
    {
      "index": 33,
      "file": "Chapter 0033 孟凉玉.md",
      "status": "pending",
      "title": "孟凉玉"
    },
    {
      "index": 34,
      "file": "Chapter 0034 怀疑.md",
      "status": "pending",
      "title": "怀疑"
    },
    {
      "index": 35,
      "file": "Chapter 0035 若是我没猜错.md",
      "status": "pending",
      "title": "若是我没猜错"
    },
    {
      "index": 36,
      "file": "Chapter 0036 找回场子.md",
      "status": "pending",
      "title": "找回场子"
    },
    {
      "index": 37,
      "file": "Chapter 0037 前尘旧事.md",
      "status": "pending",
      "title": "前尘旧事"
    },
    {
      "index": 38,
      "file": "Chapter 0038 极境.md",
      "status": "pending",
      "title": "极境"
    },
    {
      "index": 39,
      "file": "Chapter 0039 燃木（求收藏追读）.md",
      "status": "pending",
      "title": "燃木（求收藏追读）"
    },
    {
      "index": 40,
      "file": "Chapter 0040 传刀.md",
      "status": "pending",
      "title": "传刀"
    },
    {
      "index": 41,
      "file": "Chapter 0041 黑夜追杀.md",
      "status": "pending",
      "title": "黑夜追杀"
    },
    {
      "index": 42,
      "file": "Chapter 0042 帮主小心.md",
      "status": "pending",
      "title": "帮主小心"
    },
    {
      "index": 43,
      "file": "Chapter 0043 联手.md",
      "status": "pending",
      "title": "联手"
    },
    {
      "index": 44,
      "file": "Chapter 0044 家.md",
      "status": "pending",
      "title": "家"
    },
    {
      "index": 45,
      "file": "Chapter 0045 得加钱.md",
      "status": "pending",
      "title": "得加钱"
    },
    {
      "index": 46,
      "file": "Chapter 0046 劈柴刀法.md",
      "status": "pending",
      "title": "劈柴刀法"
    },
    {
      "index": 47,
      "file": "Chapter 0047 轻功.md",
      "status": "pending",
      "title": "轻功"
    },
    {
      "index": 48,
      "file": "Chapter 0048 偷人.md",
      "status": "pending",
      "title": "偷人"
    },
    {
      "index": 49,
      "file": "Chapter 0049 年关.md",
      "status": "pending",
      "title": "年关"
    },
    {
      "index": 50,
      "file": "Chapter 0050 车队.md",
      "status": "pending",
      "title": "车队"
    },
    {
      "index": 51,
      "file": "Chapter 0051 争端.md",
      "status": "pending",
      "title": "争端"
    },
    {
      "index": 52,
      "file": "Chapter 0052 震慑.md",
      "status": "pending",
      "title": "震慑"
    },
    {
      "index": 53,
      "file": "Chapter 0053 路还长.md",
      "status": "pending",
      "title": "路还长"
    },
    {
      "index": 54,
      "file": "Chapter 0054 劫匪.md",
      "status": "pending",
      "title": "劫匪"
    },
    {
      "index": 55,
      "file": "Chapter 0055 射杀.md",
      "status": "pending",
      "title": "射杀"
    },
    {
      "index": 56,
      "file": "Chapter 0056 轻骑.md",
      "status": "pending",
      "title": "轻骑"
    },
    {
      "index": 57,
      "file": "Chapter 0057 同伙.md",
      "status": "pending",
      "title": "同伙"
    },
    {
      "index": 58,
      "file": "Chapter 0058 青龙司.md",
      "status": "pending",
      "title": "青龙司"
    },
    {
      "index": 59,
      "file": "Chapter 0059 武安郡.md",
      "status": "pending",
      "title": "武安郡"
    },
    {
      "index": 60,
      "file": "Chapter 0060 东市买马.md",
      "status": "pending",
      "title": "东市买马"
    },
    {
      "index": 61,
      "file": "Chapter 0061 呼雷豹.md",
      "status": "pending",
      "title": "呼雷豹"
    },
    {
      "index": 62,
      "file": "Chapter 0062 盗弓.md",
      "status": "pending",
      "title": "盗弓"
    },
    {
      "index": 63,
      "file": "Chapter 0063 夜奔.md",
      "status": "pending",
      "title": "夜奔"
    },
    {
      "index": 64,
      "file": "Chapter 0064 莫遇老黄.md",
      "status": "pending",
      "title": "莫遇老黄"
    },
    {
      "index": 65,
      "file": "Chapter 0065 刺杀.md",
      "status": "pending",
      "title": "刺杀"
    },
    {
      "index": 66,
      "file": "Chapter 0066 赤胆忠心.md",
      "status": "pending",
      "title": "赤胆忠心"
    },
    {
      "index": 67,
      "file": "Chapter 0067 以血还血.md",
      "status": "pending",
      "title": "以血还血"
    },
    {
      "index": 68,
      "file": "Chapter 0068 大开杀戒.md",
      "status": "pending",
      "title": "大开杀戒"
    },
    {
      "index": 69,
      "file": "Chapter 0069 火烧青云楼.md",
      "status": "pending",
      "title": "火烧青云楼"
    },
    {
      "index": 70,
      "file": "Chapter 0070 让你们死个明白.md",
      "status": "pending",
      "title": "让你们死个明白"
    },
    {
      "index": 71,
      "file": "Chapter 0071 大仇得报.md",
      "status": "pending",
      "title": "大仇得报"
    },
    {
      "index": 72,
      "file": "Chapter 0072 禁书.md",
      "status": "pending",
      "title": "禁书"
    },
    {
      "index": 73,
      "file": "Chapter 0073 玄门测试.md",
      "status": "pending",
      "title": "玄门测试"
    },
    {
      "index": 74,
      "file": "Chapter 0074 算计.md",
      "status": "pending",
      "title": "算计"
    },
    {
      "index": 75,
      "file": "Chapter 0075 警觉.md",
      "status": "pending",
      "title": "警觉"
    },
    {
      "index": 76,
      "file": "Chapter 0076 李家.md",
      "status": "pending",
      "title": "李家"
    },
    {
      "index": 77,
      "file": "Chapter 0077 齐聚.md",
      "status": "pending",
      "title": "齐聚"
    },
    {
      "index": 78,
      "file": "Chapter 0078 弓不对.md",
      "status": "pending",
      "title": "弓不对"
    },
    {
      "index": 79,
      "file": "Chapter 0079 周三中午12点上架，快二十万字，不少啦。如果书看着还喜欢，希望各位书友订阅支持，老刀拜谢~.md",
      "status": "pending",
      "title": "周三中午12点上架，快二十万字，不少啦。如果书看着还喜欢，希望各位书友订阅支持，老刀拜谢~"
    },
    {
      "index": 80,
      "file": "Chapter 0080 风波.md",
      "status": "pending",
      "title": "风波"
    },
    {
      "index": 81,
      "file": "Chapter 0081 事发.md",
      "status": "pending",
      "title": "事发"
    },
    {
      "index": 82,
      "file": "Chapter 0082 引起怀疑.md",
      "status": "pending",
      "title": "引起怀疑"
    },
    {
      "index": 83,
      "file": "Chapter 0083 上架感言.md",
      "status": "pending",
      "title": "上架感言"
    },
    {
      "index": 84,
      "file": "Chapter 0084 第一卷，大雪满弓刀。.md",
      "status": "pending",
      "title": "第一卷，大雪满弓刀。"
    },
    {
      "index": 85,
      "file": "Chapter 0085 猫熊刀客（求订阅）.md",
      "status": "pending",
      "title": "猫熊刀客（求订阅）"
    },
    {
      "index": 86,
      "file": "Chapter 0086 发难（求订阅）.md",
      "status": "pending",
      "title": "发难（求订阅）"
    },
    {
      "index": 87,
      "file": "Chapter 0087 跟我混（二萌如之许加更）.md",
      "status": "pending",
      "title": "跟我混（二萌如之许加更）"
    },
    {
      "index": 88,
      "file": "Chapter 0088 飞剑？（三盟南枝加更）.md",
      "status": "pending",
      "title": "飞剑？（三盟南枝加更）"
    },
    {
      "index": 89,
      "file": "Chapter 0089 胖老头的手段.md",
      "status": "pending",
      "title": "胖老头的手段"
    },
    {
      "index": 90,
      "file": "Chapter 0090 武帝.md",
      "status": "pending",
      "title": "武帝"
    },
    {
      "index": 91,
      "file": "Chapter 0091 有点过分了.md",
      "status": "pending",
      "title": "有点过分了"
    },
    {
      "index": 92,
      "file": "Chapter 0092 其乐融融.md",
      "status": "pending",
      "title": "其乐融融"
    },
    {
      "index": 93,
      "file": "Chapter 0093 小人.md",
      "status": "pending",
      "title": "小人"
    },
    {
      "index": 94,
      "file": "Chapter 0094 官大一级.md",
      "status": "pending",
      "title": "官大一级"
    },
    {
      "index": 95,
      "file": "Chapter 0095 再上雪山.md",
      "status": "pending",
      "title": "再上雪山"
    },
    {
      "index": 96,
      "file": "Chapter 0096 诛仙术.md",
      "status": "pending",
      "title": "诛仙术"
    },
    {
      "index": 97,
      "file": "Chapter 0097 仙猿剑宗.md",
      "status": "pending",
      "title": "仙猿剑宗"
    },
    {
      "index": 98,
      "file": "Chapter 0098 白猿剑术.md",
      "status": "pending",
      "title": "白猿剑术"
    },
    {
      "index": 99,
      "file": "Chapter 0099 越界者，禽兽也.md",
      "status": "pending",
      "title": "越界者，禽兽也"
    },
    {
      "index": 100,
      "file": "Chapter 0100 入狱.md",
      "status": "pending",
      "title": "入狱"
    },
    {
      "index": 101,
      "file": "Chapter 0101 衣锦还乡.md",
      "status": "pending",
      "title": "衣锦还乡"
    },
    {
      "index": 102,
      "file": "Chapter 0102 出尔反尔.md",
      "status": "pending",
      "title": "出尔反尔"
    },
    {
      "index": 103,
      "file": "Chapter 0103 一剑封喉.md",
      "status": "pending",
      "title": "一剑封喉"
    },
    {
      "index": 104,
      "file": "Chapter 0104 杀机.md",
      "status": "pending",
      "title": "杀机"
    },
    {
      "index": 105,
      "file": "Chapter 0105 平州牧.md",
      "status": "pending",
      "title": "平州牧"
    },
    {
      "index": 106,
      "file": "Chapter 0106 练剑.md",
      "status": "pending",
      "title": "练剑"
    },
    {
      "index": 107,
      "file": "Chapter 0107 都杀了吧.md",
      "status": "pending",
      "title": "都杀了吧"
    },
    {
      "index": 108,
      "file": "Chapter 0108 霍家世子.md",
      "status": "pending",
      "title": "霍家世子"
    },
    {
      "index": 109,
      "file": "Chapter 0109 关键筹码.md",
      "status": "pending",
      "title": "关键筹码"
    },
    {
      "index": 110,
      "file": "Chapter 0110 谋反.md",
      "status": "pending",
      "title": "谋反"
    },
    {
      "index": 111,
      "file": "Chapter 0111 破局之法.md",
      "status": "pending",
      "title": "破局之法"
    },
    {
      "index": 112,
      "file": "Chapter 0112 擒龙功.md",
      "status": "pending",
      "title": "擒龙功"
    },
    {
      "index": 113,
      "file": "Chapter 0113 报复.md",
      "status": "pending",
      "title": "报复"
    },
    {
      "index": 114,
      "file": "Chapter 0114 我很惦记他.md",
      "status": "pending",
      "title": "我很惦记他"
    },
    {
      "index": 115,
      "file": "Chapter 0115 是人是鬼.md",
      "status": "pending",
      "title": "是人是鬼"
    },
    {
      "index": 116,
      "file": "Chapter 0116 扶摇功.md",
      "status": "pending",
      "title": "扶摇功"
    },
    {
      "index": 117,
      "file": "Chapter 0117 人情.md",
      "status": "pending",
      "title": "人情"
    },
    {
      "index": 118,
      "file": "Chapter 0118 刺杀.md",
      "status": "pending",
      "title": "刺杀"
    },
    {
      "index": 119,
      "file": "Chapter 0119 影子楼.md",
      "status": "pending",
      "title": "影子楼"
    },
    {
      "index": 120,
      "file": "Chapter 0120 伏击.md",
      "status": "pending",
      "title": "伏击"
    },
    {
      "index": 121,
      "file": "Chapter 0121 起事.md",
      "status": "pending",
      "title": "起事"
    },
    {
      "index": 122,
      "file": "Chapter 0122 赠刀.md",
      "status": "pending",
      "title": "赠刀"
    },
    {
      "index": 123,
      "file": "Chapter 0123 大战.md",
      "status": "pending",
      "title": "大战"
    },
    {
      "index": 124,
      "file": "Chapter 0124 三品通脉.md",
      "status": "pending",
      "title": "三品通脉"
    },
    {
      "index": 125,
      "file": "Chapter 0125 身死.md",
      "status": "pending",
      "title": "身死"
    },
    {
      "index": 126,
      "file": "Chapter 0126 归来.md",
      "status": "pending",
      "title": "归来"
    },
    {
      "index": 127,
      "file": "Chapter 0127 盗符截令.md",
      "status": "pending",
      "title": "盗符截令"
    },
    {
      "index": 128,
      "file": "Chapter 0128 欲将轻骑逐.md",
      "status": "pending",
      "title": "欲将轻骑逐"
    },
    {
      "index": 129,
      "file": "Chapter 0129 百里追杀.md",
      "status": "pending",
      "title": "百里追杀"
    },
    {
      "index": 130,
      "file": "Chapter 0130 对决.md",
      "status": "pending",
      "title": "对决"
    },
    {
      "index": 131,
      "file": "Chapter 0131 了却心事.md",
      "status": "pending",
      "title": "了却心事"
    },
    {
      "index": 132,
      "file": "Chapter 0132 再起波澜.md",
      "status": "pending",
      "title": "再起波澜"
    },
    {
      "index": 133,
      "file": "Chapter 0133 异象.md",
      "status": "pending",
      "title": "异象"
    },
    {
      "index": 134,
      "file": "Chapter 0134 决绝.md",
      "status": "pending",
      "title": "决绝"
    },
    {
      "index": 135,
      "file": "Chapter 0135 偿命.md",
      "status": "pending",
      "title": "偿命"
    },
    {
      "index": 136,
      "file": "Chapter 0136 离别.md",
      "status": "pending",
      "title": "离别"
    },
    {
      "index": 137,
      "file": "Chapter 0137 齐聚雪山.md",
      "status": "pending",
      "title": "齐聚雪山"
    },
    {
      "index": 138,
      "file": "Chapter 0138 第一卷结束，求一波月票~另外感谢往事随风一万书币的打赏~.md",
      "status": "pending",
      "title": "第一卷结束，求一波月票~另外感谢往事随风一万书币的打赏~"
    },
    {
      "index": 139,
      "file": "Chapter 0139 天下九宗.md",
      "status": "pending",
      "title": "天下九宗"
    },
    {
      "index": 140,
      "file": "Chapter 0140 朝元之意.md",
      "status": "pending",
      "title": "朝元之意"
    },
    {
      "index": 141,
      "file": "Chapter 0141 炼体和炼气.md",
      "status": "pending",
      "title": "炼体和炼气"
    },
    {
      "index": 142,
      "file": "Chapter 0142 破庙.md",
      "status": "pending",
      "title": "破庙"
    },
    {
      "index": 143,
      "file": "Chapter 0143 巫山十鬼.md",
      "status": "pending",
      "title": "巫山十鬼"
    },
    {
      "index": 144,
      "file": "Chapter 0144 全灭.md",
      "status": "pending",
      "title": "全灭"
    },
    {
      "index": 145,
      "file": "Chapter 0145 江湖这么大.md",
      "status": "pending",
      "title": "江湖这么大"
    },
    {
      "index": 146,
      "file": "Chapter 0146 毒翻.md",
      "status": "pending",
      "title": "毒翻"
    },
    {
      "index": 147,
      "file": "Chapter 0147 蛇惊了.md",
      "status": "pending",
      "title": "蛇惊了"
    },
    {
      "index": 148,
      "file": "Chapter 0148 邪祟缠身.md",
      "status": "pending",
      "title": "邪祟缠身"
    },
    {
      "index": 149,
      "file": "Chapter 0149 围杀.md",
      "status": "pending",
      "title": "围杀"
    },
    {
      "index": 150,
      "file": "Chapter 0150 潜入巫山寨.md",
      "status": "pending",
      "title": "潜入巫山寨"
    },
    {
      "index": 151,
      "file": "Chapter 0151 贡品.md",
      "status": "pending",
      "title": "贡品"
    },
    {
      "index": 152,
      "file": "Chapter 0152 大战.md",
      "status": "pending",
      "title": "大战"
    },
    {
      "index": 153,
      "file": "Chapter 0153 神照一刀.md",
      "status": "pending",
      "title": "神照一刀"
    },
    {
      "index": 154,
      "file": "Chapter 0154 团灭.md",
      "status": "pending",
      "title": "团灭"
    },
    {
      "index": 155,
      "file": "Chapter 0155 地牢.md",
      "status": "pending",
      "title": "地牢"
    },
    {
      "index": 156,
      "file": "Chapter 0156 玉笛仙子.md",
      "status": "pending",
      "title": "玉笛仙子"
    },
    {
      "index": 157,
      "file": "Chapter 0157 机关.md",
      "status": "pending",
      "title": "机关"
    },
    {
      "index": 158,
      "file": "Chapter 0158 鬼母传说.md",
      "status": "pending",
      "title": "鬼母传说"
    },
    {
      "index": 159,
      "file": "Chapter 0159 夜探.md",
      "status": "pending",
      "title": "夜探"
    },
    {
      "index": 160,
      "file": "Chapter 0160 惊艳.md",
      "status": "pending",
      "title": "惊艳"
    },
    {
      "index": 161,
      "file": "Chapter 0161 剑丸.md",
      "status": "pending",
      "title": "剑丸"
    },
    {
      "index": 162,
      "file": "Chapter 0162 身死.md",
      "status": "pending",
      "title": "身死"
    },
    {
      "index": 163,
      "file": "Chapter 0163 逃离.md",
      "status": "pending",
      "title": "逃离"
    },
    {
      "index": 164,
      "file": "Chapter 0164 飞星步.md",
      "status": "pending",
      "title": "飞星步"
    },
    {
      "index": 165,
      "file": "Chapter 0165 追踪术.md",
      "status": "pending",
      "title": "追踪术"
    },
    {
      "index": 166,
      "file": "Chapter 0166 缘分.md",
      "status": "pending",
      "title": "缘分"
    },
    {
      "index": 167,
      "file": "Chapter 0167 无法脱身.md",
      "status": "pending",
      "title": "无法脱身"
    },
    {
      "index": 168,
      "file": "Chapter 0168 美妇.md",
      "status": "pending",
      "title": "美妇"
    },
    {
      "index": 169,
      "file": "Chapter 0169 杀心.md",
      "status": "pending",
      "title": "杀心"
    },
    {
      "index": 170,
      "file": "Chapter 0170 夏江之战.md",
      "status": "pending",
      "title": "夏江之战"
    },
    {
      "index": 171,
      "file": "Chapter 0171 陆千山.md",
      "status": "pending",
      "title": "陆千山"
    },
    {
      "index": 172,
      "file": "Chapter 0172 武帝后人.md",
      "status": "pending",
      "title": "武帝后人"
    },
    {
      "index": 173,
      "file": "Chapter 0173 魏王.md",
      "status": "pending",
      "title": "魏王"
    },
    {
      "index": 174,
      "file": "Chapter 0174 四方云动.md",
      "status": "pending",
      "title": "四方云动"
    },
    {
      "index": 175,
      "file": "Chapter 0175 宽仁帝王.md",
      "status": "pending",
      "title": "宽仁帝王"
    },
    {
      "index": 176,
      "file": "Chapter 0176 京城之变.md",
      "status": "pending",
      "title": "京城之变"
    },
    {
      "index": 177,
      "file": "Chapter 0177 瞒天过海.md",
      "status": "pending",
      "title": "瞒天过海"
    },
    {
      "index": 178,
      "file": "Chapter 0178 白虎司.md",
      "status": "pending",
      "title": "白虎司"
    },
    {
      "index": 179,
      "file": "Chapter 0179 八方云集.md",
      "status": "pending",
      "title": "八方云集"
    },
    {
      "index": 180,
      "file": "Chapter 0180 少帅.md",
      "status": "pending",
      "title": "少帅"
    },
    {
      "index": 181,
      "file": "Chapter 0181 到此为止.md",
      "status": "pending",
      "title": "到此为止"
    },
    {
      "index": 182,
      "file": "Chapter 0182 太尉令.md",
      "status": "pending",
      "title": "太尉令"
    },
    {
      "index": 183,
      "file": "Chapter 0183 有！.md",
      "status": "pending",
      "title": "有！"
    },
    {
      "index": 184,
      "file": "Chapter 0184 狠人.md",
      "status": "pending",
      "title": "狠人"
    },
    {
      "index": 185,
      "file": "Chapter 0185 兵分四路.md",
      "status": "pending",
      "title": "兵分四路"
    },
    {
      "index": 186,
      "file": "Chapter 0186 死生同（4000字章节）.md",
      "status": "pending",
      "title": "死生同（4000字章节）"
    },
    {
      "index": 187,
      "file": "Chapter 0187 功亏一篑.md",
      "status": "pending",
      "title": "功亏一篑"
    },
    {
      "index": 188,
      "file": "Chapter 0188 叶雨时.md",
      "status": "pending",
      "title": "叶雨时"
    },
    {
      "index": 189,
      "file": "Chapter 0189 虎豹之音.md",
      "status": "pending",
      "title": "虎豹之音"
    },
    {
      "index": 190,
      "file": "Chapter 0190 杀了便是.md",
      "status": "pending",
      "title": "杀了便是"
    },
    {
      "index": 191,
      "file": "Chapter 0191 寒意.md",
      "status": "pending",
      "title": "寒意"
    },
    {
      "index": 192,
      "file": "Chapter 0192 邪帝.md",
      "status": "pending",
      "title": "邪帝"
    },
    {
      "index": 193,
      "file": "Chapter 0193 虎啸龙吟.md",
      "status": "pending",
      "title": "虎啸龙吟"
    },
    {
      "index": 194,
      "file": "Chapter 0194 出山.md",
      "status": "pending",
      "title": "出山"
    },
    {
      "index": 195,
      "file": "Chapter 0195 相互利用.md",
      "status": "pending",
      "title": "相互利用"
    },
    {
      "index": 196,
      "file": "Chapter 0196 金刚舍利.md",
      "status": "pending",
      "title": "金刚舍利"
    },
    {
      "index": 197,
      "file": "Chapter 0197 禅宗.md",
      "status": "pending",
      "title": "禅宗"
    },
    {
      "index": 198,
      "file": "Chapter 0198 封印.md",
      "status": "pending",
      "title": "封印"
    },
    {
      "index": 199,
      "file": "Chapter 0199 果然是神经病.md",
      "status": "pending",
      "title": "果然是神经病"
    },
    {
      "index": 200,
      "file": "Chapter 0200 西陵密宗.md",
      "status": "pending",
      "title": "西陵密宗"
    },
    {
      "index": 201,
      "file": "Chapter 0201 明元师兄.md",
      "status": "pending",
      "title": "明元师兄"
    },
    {
      "index": 202,
      "file": "Chapter 0202 师兄上道.md",
      "status": "pending",
      "title": "师兄上道"
    },
    {
      "index": 203,
      "file": "Chapter 0203 罗汉伏魔拳.md",
      "status": "pending",
      "title": "罗汉伏魔拳"
    },
    {
      "index": 204,
      "file": "Chapter 0204 十六罗汉.md",
      "status": "pending",
      "title": "十六罗汉"
    },
    {
      "index": 205,
      "file": "Chapter 0205 占便宜没够.md",
      "status": "pending",
      "title": "占便宜没够"
    },
    {
      "index": 206,
      "file": "Chapter 0206 密宗大手印.md",
      "status": "pending",
      "title": "密宗大手印"
    },
    {
      "index": 207,
      "file": "Chapter 0207 该我了.md",
      "status": "pending",
      "title": "该我了"
    },
    {
      "index": 208,
      "file": "Chapter 0208 转世金刚.md",
      "status": "pending",
      "title": "转世金刚"
    },
    {
      "index": 209,
      "file": "Chapter 0209 跪拜.md",
      "status": "pending",
      "title": "跪拜"
    },
    {
      "index": 210,
      "file": "Chapter 0210 收获巨大.md",
      "status": "pending",
      "title": "收获巨大"
    },
    {
      "index": 211,
      "file": "Chapter 0211 洗髓.md",
      "status": "pending",
      "title": "洗髓"
    },
    {
      "index": 212,
      "file": "Chapter 0212 如雷贯耳.md",
      "status": "pending",
      "title": "如雷贯耳"
    },
    {
      "index": 213,
      "file": "Chapter 0213 赦免.md",
      "status": "pending",
      "title": "赦免"
    },
    {
      "index": 214,
      "file": "Chapter 0214 麒麟榜.md",
      "status": "pending",
      "title": "麒麟榜"
    },
    {
      "index": 215,
      "file": "Chapter 0215 蛮族少年.md",
      "status": "pending",
      "title": "蛮族少年"
    },
    {
      "index": 216,
      "file": "Chapter 0216 三封信.md",
      "status": "pending",
      "title": "三封信"
    },
    {
      "index": 217,
      "file": "Chapter 0217 否极泰来.md",
      "status": "pending",
      "title": "否极泰来"
    },
    {
      "index": 218,
      "file": "Chapter 0218 京城冲突.md",
      "status": "pending",
      "title": "京城冲突"
    },
    {
      "index": 219,
      "file": "Chapter 0219 训斥.md",
      "status": "pending",
      "title": "训斥"
    },
    {
      "index": 220,
      "file": "Chapter 0220 玄天教主.md",
      "status": "pending",
      "title": "玄天教主"
    },
    {
      "index": 221,
      "file": "Chapter 0221 扼杀未来宗师.md",
      "status": "pending",
      "title": "扼杀未来宗师"
    },
    {
      "index": 222,
      "file": "Chapter 0222 声势.md",
      "status": "pending",
      "title": "声势"
    },
    {
      "index": 223,
      "file": "Chapter 0223 大战.md",
      "status": "pending",
      "title": "大战"
    },
    {
      "index": 224,
      "file": "Chapter 0224 秘法.md",
      "status": "pending",
      "title": "秘法"
    },
    {
      "index": 225,
      "file": "Chapter 0225 送你上路.md",
      "status": "pending",
      "title": "送你上路"
    },
    {
      "index": 226,
      "file": "Chapter 0226 杀！.md",
      "status": "pending",
      "title": "杀！"
    },
    {
      "index": 227,
      "file": "Chapter 0227 狮虎罗汉.md",
      "status": "pending",
      "title": "狮虎罗汉"
    },
    {
      "index": 228,
      "file": "Chapter 0228 暗流涌动.md",
      "status": "pending",
      "title": "暗流涌动"
    },
    {
      "index": 229,
      "file": "Chapter 0229 雷系天赋.md",
      "status": "pending",
      "title": "雷系天赋"
    },
    {
      "index": 230,
      "file": "Chapter 0230 盛世.md",
      "status": "pending",
      "title": "盛世"
    },
    {
      "index": 231,
      "file": "Chapter 0231 后宫比斗.md",
      "status": "pending",
      "title": "后宫比斗"
    },
    {
      "index": 232,
      "file": "Chapter 0232 废了.md",
      "status": "pending",
      "title": "废了"
    },
    {
      "index": 233,
      "file": "Chapter 0233 为玄门正名.md",
      "status": "pending",
      "title": "为玄门正名"
    },
    {
      "index": 234,
      "file": "Chapter 0234 见血.md",
      "status": "pending",
      "title": "见血"
    },
    {
      "index": 235,
      "file": "Chapter 0235 不祥.md",
      "status": "pending",
      "title": "不祥"
    },
    {
      "index": 236,
      "file": "Chapter 0236 罪己.md",
      "status": "pending",
      "title": "罪己"
    },
    {
      "index": 237,
      "file": "Chapter 0237 信错了人.md",
      "status": "pending",
      "title": "信错了人"
    },
    {
      "index": 238,
      "file": "Chapter 0238 天谴.md",
      "status": "pending",
      "title": "天谴"
    },
    {
      "index": 239,
      "file": "Chapter 0239 天书.md",
      "status": "pending",
      "title": "天书"
    },
    {
      "index": 240,
      "file": "Chapter 0240 万古.md",
      "status": "pending",
      "title": "万古"
    },
    {
      "index": 241,
      "file": "Chapter 0241 太仆寺.md",
      "status": "pending",
      "title": "太仆寺"
    },
    {
      "index": 242,
      "file": "Chapter 0242 离别.md",
      "status": "pending",
      "title": "离别"
    },
    {
      "index": 243,
      "file": "Chapter 0243 各生欢喜.md",
      "status": "pending",
      "title": "各生欢喜"
    },
    {
      "index": 244,
      "file": "Chapter 0244 青州.md",
      "status": "pending",
      "title": "青州"
    },
    {
      "index": 245,
      "file": "Chapter 0245 真相.md",
      "status": "pending",
      "title": "真相"
    },
    {
      "index": 246,
      "file": "Chapter 0246 针对.md",
      "status": "pending",
      "title": "针对"
    },
    {
      "index": 247,
      "file": "Chapter 0247 血祭‘万古’.md",
      "status": "pending",
      "title": "血祭‘万古’"
    },
    {
      "index": 248,
      "file": "Chapter 0248 夜探.md",
      "status": "pending",
      "title": "夜探"
    },
    {
      "index": 249,
      "file": "Chapter 0249 杀穿玄天观.md",
      "status": "pending",
      "title": "杀穿玄天观"
    },
    {
      "index": 250,
      "file": "Chapter 0250 一刀结果.md",
      "status": "pending",
      "title": "一刀结果"
    },
    {
      "index": 251,
      "file": "Chapter 0251 修罗.md",
      "status": "pending",
      "title": "修罗"
    },
    {
      "index": 252,
      "file": "Chapter 0252 四方云动.md",
      "status": "pending",
      "title": "四方云动"
    },
    {
      "index": 253,
      "file": "Chapter 0253 谭都统.md",
      "status": "pending",
      "title": "谭都统"
    },
    {
      "index": 254,
      "file": "Chapter 0254 古怪村落.md",
      "status": "pending",
      "title": "古怪村落"
    },
    {
      "index": 255,
      "file": "Chapter 0255 快刀斩乱麻.md",
      "status": "pending",
      "title": "快刀斩乱麻"
    },
    {
      "index": 256,
      "file": "Chapter 0256 有缘之人.md",
      "status": "pending",
      "title": "有缘之人"
    },
    {
      "index": 257,
      "file": "Chapter 0257 双龙.md",
      "status": "pending",
      "title": "双龙"
    },
    {
      "index": 258,
      "file": "Chapter 0258 再灭一观.md",
      "status": "pending",
      "title": "再灭一观"
    },
    {
      "index": 259,
      "file": "Chapter 0259 笼中之鸟.md",
      "status": "pending",
      "title": "笼中之鸟"
    },
    {
      "index": 260,
      "file": "Chapter 0260 谭某的剑，可还锋利？.md",
      "status": "pending",
      "title": "谭某的剑，可还锋利？"
    },
    {
      "index": 261,
      "file": "Chapter 0261 血战长街.md",
      "status": "pending",
      "title": "血战长街"
    },
    {
      "index": 262,
      "file": "Chapter 0262 逃出生天.md",
      "status": "pending",
      "title": "逃出生天"
    },
    {
      "index": 263,
      "file": "Chapter 0263 广阔天地.md",
      "status": "pending",
      "title": "广阔天地"
    },
    {
      "index": 264,
      "file": "Chapter 0264 惊变.md",
      "status": "pending",
      "title": "惊变"
    },
    {
      "index": 265,
      "file": "Chapter 0265 屠蛟.md",
      "status": "pending",
      "title": "屠蛟"
    },
    {
      "index": 266,
      "file": "Chapter 0266 开膛破肚.md",
      "status": "pending",
      "title": "开膛破肚"
    },
    {
      "index": 267,
      "file": "Chapter 0267 插翅难逃.md",
      "status": "pending",
      "title": "插翅难逃"
    },
    {
      "index": 268,
      "file": "Chapter 0268 祸水东引.md",
      "status": "pending",
      "title": "祸水东引"
    },
    {
      "index": 269,
      "file": "Chapter 0269 真正目的.md",
      "status": "pending",
      "title": "真正目的"
    },
    {
      "index": 270,
      "file": "Chapter 0270 化境之战.md",
      "status": "pending",
      "title": "化境之战"
    },
    {
      "index": 271,
      "file": "Chapter 0271 反杀.md",
      "status": "pending",
      "title": "反杀"
    },
    {
      "index": 272,
      "file": "Chapter 0272 龙焰.md",
      "status": "pending",
      "title": "龙焰"
    },
    {
      "index": 273,
      "file": "Chapter 0273 巨妖.md",
      "status": "pending",
      "title": "巨妖"
    },
    {
      "index": 274,
      "file": "Chapter 0274 第三卷，终。.md",
      "status": "pending",
      "title": "第三卷，终。"
    },
    {
      "index": 275,
      "file": "Chapter 0275 名传天下.md",
      "status": "pending",
      "title": "名传天下"
    },
    {
      "index": 276,
      "file": "Chapter 0276 死里逃生.md",
      "status": "pending",
      "title": "死里逃生"
    },
    {
      "index": 277,
      "file": "Chapter 0277 性格温顺.md",
      "status": "pending",
      "title": "性格温顺"
    },
    {
      "index": 278,
      "file": "Chapter 0278 海底深渊.md",
      "status": "pending",
      "title": "海底深渊"
    },
    {
      "index": 279,
      "file": "Chapter 0279 沧海悟道.md",
      "status": "pending",
      "title": "沧海悟道"
    },
    {
      "index": 280,
      "file": "Chapter 0280 呼吸之法.md",
      "status": "pending",
      "title": "呼吸之法"
    },
    {
      "index": 281,
      "file": "Chapter 0281 内壮脏腑.md",
      "status": "pending",
      "title": "内壮脏腑"
    },
    {
      "index": 282,
      "file": "Chapter 0282 深海苦练.md",
      "status": "pending",
      "title": "深海苦练"
    },
    {
      "index": 283,
      "file": "Chapter 0283 请假一天.md",
      "status": "pending",
      "title": "请假一天"
    },
    {
      "index": 284,
      "file": "Chapter 0284 请假一天.md",
      "status": "pending",
      "title": "请假一天"
    },
    {
      "index": 285,
      "file": "Chapter 0285 上岸.md",
      "status": "pending",
      "title": "上岸"
    },
    {
      "index": 286,
      "file": "Chapter 0286 敌意.md",
      "status": "pending",
      "title": "敌意"
    },
    {
      "index": 287,
      "file": "Chapter 0287 隐者洲.md",
      "status": "pending",
      "title": "隐者洲"
    },
    {
      "index": 288,
      "file": "Chapter 0288 沈钰.md",
      "status": "pending",
      "title": "沈钰"
    },
    {
      "index": 289,
      "file": "Chapter 0289 今非昔比.md",
      "status": "pending",
      "title": "今非昔比"
    },
    {
      "index": 290,
      "file": "Chapter 0290 武朝中人？.md",
      "status": "pending",
      "title": "武朝中人？"
    },
    {
      "index": 291,
      "file": "Chapter 0291 隐者守则.md",
      "status": "pending",
      "title": "隐者守则"
    },
    {
      "index": 292,
      "file": "Chapter 0292 全灭.md",
      "status": "pending",
      "title": "全灭"
    },
    {
      "index": 293,
      "file": "Chapter 0293 血光之灾.md",
      "status": "pending",
      "title": "血光之灾"
    },
    {
      "index": 294,
      "file": "Chapter 0294 老铁匠.md",
      "status": "pending",
      "title": "老铁匠"
    },
    {
      "index": 295,
      "file": "Chapter 0295 老板娘.md",
      "status": "pending",
      "title": "老板娘"
    },
    {
      "index": 296,
      "file": "Chapter 0296 再见故人.md",
      "status": "pending",
      "title": "再见故人"
    },
    {
      "index": 297,
      "file": "Chapter 0297 悬赏任务.md",
      "status": "pending",
      "title": "悬赏任务"
    },
    {
      "index": 298,
      "file": "Chapter 0298 送行酒.md",
      "status": "pending",
      "title": "送行酒"
    },
    {
      "index": 299,
      "file": "Chapter 0299 赌局.md",
      "status": "pending",
      "title": "赌局"
    },
    {
      "index": 300,
      "file": "Chapter 0300 大战.md",
      "status": "pending",
      "title": "大战"
    },
    {
      "index": 301,
      "file": "Chapter 0301 杀戮.md",
      "status": "pending",
      "title": "杀戮"
    },
    {
      "index": 302,
      "file": "Chapter 0302 危险级.md",
      "status": "pending",
      "title": "危险级"
    },
    {
      "index": 303,
      "file": "Chapter 0303 五毒散.md",
      "status": "pending",
      "title": "五毒散"
    },
    {
      "index": 304,
      "file": "Chapter 0304 警告.md",
      "status": "pending",
      "title": "警告"
    },
    {
      "index": 305,
      "file": "Chapter 0305 观想之法.md",
      "status": "pending",
      "title": "观想之法"
    },
    {
      "index": 306,
      "file": "Chapter 0306 神仙眷侣.md",
      "status": "pending",
      "title": "神仙眷侣"
    },
    {
      "index": 307,
      "file": "Chapter 0307 帮你上药.md",
      "status": "pending",
      "title": "帮你上药"
    },
    {
      "index": 308,
      "file": "Chapter 0308 过来人.md",
      "status": "pending",
      "title": "过来人"
    },
    {
      "index": 309,
      "file": "Chapter 0309 噩梦.md",
      "status": "pending",
      "title": "噩梦"
    },
    {
      "index": 310,
      "file": "Chapter 0310 隐秘.md",
      "status": "pending",
      "title": "隐秘"
    },
    {
      "index": 311,
      "file": "Chapter 0311 衣不如新.md",
      "status": "pending",
      "title": "衣不如新"
    },
    {
      "index": 312,
      "file": "Chapter 0312 我回来了！.md",
      "status": "pending",
      "title": "我回来了！"
    },
    {
      "index": 313,
      "file": "Chapter 0313 暗榜.md",
      "status": "pending",
      "title": "暗榜"
    },
    {
      "index": 314,
      "file": "Chapter 0314 毒手.md",
      "status": "pending",
      "title": "毒手"
    },
    {
      "index": 315,
      "file": "Chapter 0315 烟中恶鬼.md",
      "status": "pending",
      "title": "烟中恶鬼"
    },
    {
      "index": 316,
      "file": "Chapter 0316 最后的毒手.md",
      "status": "pending",
      "title": "最后的毒手"
    },
    {
      "index": 317,
      "file": "Chapter 0317 遇强则强.md",
      "status": "pending",
      "title": "遇强则强"
    },
    {
      "index": 318,
      "file": "Chapter 0318 悬赏增加.md",
      "status": "pending",
      "title": "悬赏增加"
    },
    {
      "index": 319,
      "file": "Chapter 0319 沧海诀.md",
      "status": "pending",
      "title": "沧海诀"
    },
    {
      "index": 320,
      "file": "Chapter 0320 凶！.md",
      "status": "pending",
      "title": "凶！"
    },
    {
      "index": 321,
      "file": "Chapter 0321 大战！.md",
      "status": "pending",
      "title": "大战！"
    },
    {
      "index": 322,
      "file": "Chapter 0322 不分敌我.md",
      "status": "pending",
      "title": "不分敌我"
    },
    {
      "index": 323,
      "file": "Chapter 0323 你上当了.md",
      "status": "pending",
      "title": "你上当了"
    },
    {
      "index": 324,
      "file": "Chapter 0324 连杀！（大章）.md",
      "status": "pending",
      "title": "连杀！（大章）"
    },
    {
      "index": 325,
      "file": "Chapter 0325 一醉方休.md",
      "status": "pending",
      "title": "一醉方休"
    },
    {
      "index": 326,
      "file": "Chapter 0326 鬼隐来历.md",
      "status": "pending",
      "title": "鬼隐来历"
    },
    {
      "index": 327,
      "file": "Chapter 0327 诛杀令.md",
      "status": "pending",
      "title": "诛杀令"
    },
    {
      "index": 328,
      "file": "Chapter 0328 为我送行.md",
      "status": "pending",
      "title": "为我送行"
    },
    {
      "index": 329,
      "file": "Chapter 0329 公道.md",
      "status": "pending",
      "title": "公道"
    },
    {
      "index": 330,
      "file": "Chapter 0330 瞬杀.md",
      "status": "pending",
      "title": "瞬杀"
    },
    {
      "index": 331,
      "file": "Chapter 0331 联手.md",
      "status": "pending",
      "title": "联手"
    },
    {
      "index": 332,
      "file": "Chapter 0332 纳命来！.md",
      "status": "pending",
      "title": "纳命来！"
    },
    {
      "index": 333,
      "file": "Chapter 0333 大开杀戒.md",
      "status": "pending",
      "title": "大开杀戒"
    },
    {
      "index": 334,
      "file": "Chapter 0334 斩三品.md",
      "status": "pending",
      "title": "斩三品"
    },
    {
      "index": 335,
      "file": "Chapter 0335 第四位上隐.md",
      "status": "pending",
      "title": "第四位上隐"
    },
    {
      "index": 336,
      "file": "Chapter 0336 船上激战.md",
      "status": "pending",
      "title": "船上激战"
    },
    {
      "index": 337,
      "file": "Chapter 0337 葬身海底.md",
      "status": "pending",
      "title": "葬身海底"
    },
    {
      "index": 338,
      "file": "Chapter 0338 全身而退.md",
      "status": "pending",
      "title": "全身而退"
    },
    {
      "index": 339,
      "file": "Chapter 0339 神迹.md",
      "status": "pending",
      "title": "神迹"
    },
    {
      "index": 340,
      "file": "Chapter 0340 套近乎.md",
      "status": "pending",
      "title": "套近乎"
    },
    {
      "index": 341,
      "file": "Chapter 0341 密令.md",
      "status": "pending",
      "title": "密令"
    },
    {
      "index": 342,
      "file": "Chapter 0342 真假.md",
      "status": "pending",
      "title": "真假"
    },
    {
      "index": 343,
      "file": "Chapter 0343 天才战.md",
      "status": "pending",
      "title": "天才战"
    },
    {
      "index": 344,
      "file": "Chapter 0344 夸下海口.md",
      "status": "pending",
      "title": "夸下海口"
    },
    {
      "index": 345,
      "file": "Chapter 0345 敲打.md",
      "status": "pending",
      "title": "敲打"
    },
    {
      "index": 346,
      "file": "Chapter 0346 八大金刚.md",
      "status": "pending",
      "title": "八大金刚"
    },
    {
      "index": 347,
      "file": "Chapter 0347 吓尿了.md",
      "status": "pending",
      "title": "吓尿了"
    },
    {
      "index": 348,
      "file": "Chapter 0348 孤鸿刀（盟主上官雨林加更）.md",
      "status": "pending",
      "title": "孤鸿刀（盟主上官雨林加更）"
    },
    {
      "index": 349,
      "file": "Chapter 0349 气急败坏（盟主咸四羽加更）.md",
      "status": "pending",
      "title": "气急败坏（盟主咸四羽加更）"
    },
    {
      "index": 350,
      "file": "Chapter 0350 炎之力.md",
      "status": "pending",
      "title": "炎之力"
    },
    {
      "index": 351,
      "file": "Chapter 0351 神器异变.md",
      "status": "pending",
      "title": "神器异变"
    },
    {
      "index": 352,
      "file": "Chapter 0352 伏虎！.md",
      "status": "pending",
      "title": "伏虎！"
    },
    {
      "index": 353,
      "file": "Chapter 0353 守护荣耀.md",
      "status": "pending",
      "title": "守护荣耀"
    },
    {
      "index": 354,
      "file": "Chapter 0354 开幕.md",
      "status": "pending",
      "title": "开幕"
    },
    {
      "index": 355,
      "file": "Chapter 0355 搞事情.md",
      "status": "pending",
      "title": "搞事情"
    },
    {
      "index": 356,
      "file": "Chapter 0356 相扑之术.md",
      "status": "pending",
      "title": "相扑之术"
    },
    {
      "index": 357,
      "file": "Chapter 0357 我不是针对你.md",
      "status": "pending",
      "title": "我不是针对你"
    },
    {
      "index": 358,
      "file": "Chapter 0358 火上浇油.md",
      "status": "pending",
      "title": "火上浇油"
    },
    {
      "index": 359,
      "file": "Chapter 0359 败！败！败！.md",
      "status": "pending",
      "title": "败！败！败！"
    },
    {
      "index": 360,
      "file": "Chapter 0360 你的刀太慢了.md",
      "status": "pending",
      "title": "你的刀太慢了"
    },
    {
      "index": 361,
      "file": "Chapter 0361 夺剑.md",
      "status": "pending",
      "title": "夺剑"
    },
    {
      "index": 362,
      "file": "Chapter 0362 自尽.md",
      "status": "pending",
      "title": "自尽"
    },
    {
      "index": 363,
      "file": "Chapter 0363 怕了怕了.md",
      "status": "pending",
      "title": "怕了怕了"
    },
    {
      "index": 364,
      "file": "Chapter 0364 强势无敌.md",
      "status": "pending",
      "title": "强势无敌"
    },
    {
      "index": 365,
      "file": "Chapter 0365 打哭了！.md",
      "status": "pending",
      "title": "打哭了！"
    },
    {
      "index": 366,
      "file": "Chapter 0366 杀！.md",
      "status": "pending",
      "title": "杀！"
    },
    {
      "index": 367,
      "file": "Chapter 0367 琅琊阁.md",
      "status": "pending",
      "title": "琅琊阁"
    },
    {
      "index": 368,
      "file": "Chapter 0368 截杀.md",
      "status": "pending",
      "title": "截杀"
    },
    {
      "index": 369,
      "file": "Chapter 0369 人才啊.md",
      "status": "pending",
      "title": "人才啊"
    },
    {
      "index": 370,
      "file": "Chapter 0370 武帝刀意.md",
      "status": "pending",
      "title": "武帝刀意"
    },
    {
      "index": 371,
      "file": "Chapter 0371 当时明月在.md",
      "status": "pending",
      "title": "当时明月在"
    },
    {
      "index": 372,
      "file": "Chapter 0372 浮光掠影.md",
      "status": "pending",
      "title": "浮光掠影"
    },
    {
      "index": 373,
      "file": "Chapter 0373 剑出东山.md",
      "status": "pending",
      "title": "剑出东山"
    },
    {
      "index": 374,
      "file": "Chapter 0374 背后推手.md",
      "status": "pending",
      "title": "背后推手"
    },
    {
      "index": 375,
      "file": "Chapter 0375 沧海横流（完）.md",
      "status": "pending",
      "title": "沧海横流（完）"
    },
    {
      "index": 376,
      "file": "Chapter 0376 他就是神！.md",
      "status": "pending",
      "title": "他就是神！"
    },
    {
      "index": 377,
      "file": "Chapter 0377 抵达南夏.md",
      "status": "pending",
      "title": "抵达南夏"
    },
    {
      "index": 378,
      "file": "Chapter 0378 茶道门.md",
      "status": "pending",
      "title": "茶道门"
    },
    {
      "index": 379,
      "file": "Chapter 0379 知微下落.md",
      "status": "pending",
      "title": "知微下落"
    },
    {
      "index": 380,
      "file": "Chapter 0380 冲突.md",
      "status": "pending",
      "title": "冲突"
    },
    {
      "index": 381,
      "file": "Chapter 0381 青梅剑侠.md",
      "status": "pending",
      "title": "青梅剑侠"
    },
    {
      "index": 382,
      "file": "Chapter 0382 江湖险恶.md",
      "status": "pending",
      "title": "江湖险恶"
    },
    {
      "index": 383,
      "file": "Chapter 0383 丧命.md",
      "status": "pending",
      "title": "丧命"
    },
    {
      "index": 384,
      "file": "Chapter 0384 围攻.md",
      "status": "pending",
      "title": "围攻"
    },
    {
      "index": 385,
      "file": "Chapter 0385 送他上路！.md",
      "status": "pending",
      "title": "送他上路！"
    },
    {
      "index": 386,
      "file": "Chapter 0386 恋尸癖.md",
      "status": "pending",
      "title": "恋尸癖"
    },
    {
      "index": 387,
      "file": "Chapter 0387 铸剑山庄.md",
      "status": "pending",
      "title": "铸剑山庄"
    },
    {
      "index": 388,
      "file": "Chapter 0388 苏老太君.md",
      "status": "pending",
      "title": "苏老太君"
    },
    {
      "index": 389,
      "file": "Chapter 0389 天骄聚首.md",
      "status": "pending",
      "title": "天骄聚首"
    },
    {
      "index": 390,
      "file": "Chapter 0390 给江湖一点震撼.md",
      "status": "pending",
      "title": "给江湖一点震撼"
    },
    {
      "index": 391,
      "file": "Chapter 0391 变故.md",
      "status": "pending",
      "title": "变故"
    },
    {
      "index": 392,
      "file": "Chapter 0392 杀！.md",
      "status": "pending",
      "title": "杀！"
    },
    {
      "index": 393,
      "file": "Chapter 0393 上山.md",
      "status": "pending",
      "title": "上山"
    },
    {
      "index": 394,
      "file": "Chapter 0394 堕落了？.md",
      "status": "pending",
      "title": "堕落了？"
    },
    {
      "index": 395,
      "file": "Chapter 0395 琅琊阁阁主.md",
      "status": "pending",
      "title": "琅琊阁阁主"
    },
    {
      "index": 396,
      "file": "Chapter 0396 破除心魔.md",
      "status": "pending",
      "title": "破除心魔"
    },
    {
      "index": 397,
      "file": "Chapter 0397 铸剑.md",
      "status": "pending",
      "title": "铸剑"
    },
    {
      "index": 398,
      "file": "Chapter 0398 临河序.md",
      "status": "pending",
      "title": "临河序"
    },
    {
      "index": 399,
      "file": "Chapter 0399 风云聚首.md",
      "status": "pending",
      "title": "风云聚首"
    },
    {
      "index": 400,
      "file": "Chapter 0400 酒有问题？.md",
      "status": "pending",
      "title": "酒有问题？"
    },
    {
      "index": 401,
      "file": "Chapter 0401 罚酒.md",
      "status": "pending",
      "title": "罚酒"
    },
    {
      "index": 402,
      "file": "Chapter 0402 故人重逢.md",
      "status": "pending",
      "title": "故人重逢"
    },
    {
      "index": 403,
      "file": "Chapter 0403 提鞋都不配！.md",
      "status": "pending",
      "title": "提鞋都不配！"
    },
    {
      "index": 404,
      "file": "Chapter 0404 玄帅（第五更）.md",
      "status": "pending",
      "title": "玄帅（第五更）"
    },
    {
      "index": 405,
      "file": "Chapter 0405 心机.md",
      "status": "pending",
      "title": "心机"
    },
    {
      "index": 406,
      "file": "Chapter 0406 有眼无珠！.md",
      "status": "pending",
      "title": "有眼无珠！"
    },
    {
      "index": 407,
      "file": "Chapter 0407 神秘符号.md",
      "status": "pending",
      "title": "神秘符号"
    },
    {
      "index": 408,
      "file": "Chapter 0408 醉翁.md",
      "status": "pending",
      "title": "醉翁"
    },
    {
      "index": 409,
      "file": "Chapter 0409 约战之日.md",
      "status": "pending",
      "title": "约战之日"
    },
    {
      "index": 410,
      "file": "Chapter 0410 变故.md",
      "status": "pending",
      "title": "变故"
    },
    {
      "index": 411,
      "file": "Chapter 0411 看走眼了.md",
      "status": "pending",
      "title": "看走眼了"
    },
    {
      "index": 412,
      "file": "Chapter 0412 坐井观天.md",
      "status": "pending",
      "title": "坐井观天"
    },
    {
      "index": 413,
      "file": "Chapter 0413 不过如此.md",
      "status": "pending",
      "title": "不过如此"
    },
    {
      "index": 414,
      "file": "Chapter 0414 无名之辈.md",
      "status": "pending",
      "title": "无名之辈"
    },
    {
      "index": 415,
      "file": "Chapter 0415 拿你试剑.md",
      "status": "pending",
      "title": "拿你试剑"
    },
    {
      "index": 416,
      "file": "Chapter 0416 黥面.md",
      "status": "pending",
      "title": "黥面"
    },
    {
      "index": 417,
      "file": "Chapter 0417 再生变数.md",
      "status": "pending",
      "title": "再生变数"
    },
    {
      "index": 418,
      "file": "Chapter 0418 胜负已分.md",
      "status": "pending",
      "title": "胜负已分"
    },
    {
      "index": 419,
      "file": "Chapter 0419 门当户对.md",
      "status": "pending",
      "title": "门当户对"
    },
    {
      "index": 420,
      "file": "Chapter 0420 叶玄不对劲.md",
      "status": "pending",
      "title": "叶玄不对劲"
    },
    {
      "index": 421,
      "file": "Chapter 0421 缘分天定.md",
      "status": "pending",
      "title": "缘分天定"
    },
    {
      "index": 422,
      "file": "Chapter 0422 事发.md",
      "status": "pending",
      "title": "事发"
    },
    {
      "index": 423,
      "file": "Chapter 0423 借力.md",
      "status": "pending",
      "title": "借力"
    },
    {
      "index": 424,
      "file": "Chapter 0424 发难.md",
      "status": "pending",
      "title": "发难"
    },
    {
      "index": 425,
      "file": "Chapter 0425 一石三鸟.md",
      "status": "pending",
      "title": "一石三鸟"
    },
    {
      "index": 426,
      "file": "Chapter 0426 一记耳光.md",
      "status": "pending",
      "title": "一记耳光"
    },
    {
      "index": 427,
      "file": "Chapter 0427 人，你带不走.md",
      "status": "pending",
      "title": "人，你带不走"
    },
    {
      "index": 428,
      "file": "Chapter 0428 格杀勿论！.md",
      "status": "pending",
      "title": "格杀勿论！"
    },
    {
      "index": 429,
      "file": "Chapter 0429 名动京华.md",
      "status": "pending",
      "title": "名动京华"
    },
    {
      "index": 430,
      "file": "Chapter 0430 老阁主的信.md",
      "status": "pending",
      "title": "老阁主的信"
    },
    {
      "index": 431,
      "file": "Chapter 0431 长生真君.md",
      "status": "pending",
      "title": "长生真君"
    },
    {
      "index": 432,
      "file": "Chapter 0432 梅花易主.md",
      "status": "pending",
      "title": "梅花易主"
    },
    {
      "index": 433,
      "file": "Chapter 0433 解决尾巴.md",
      "status": "pending",
      "title": "解决尾巴"
    },
    {
      "index": 434,
      "file": "Chapter 0434 战火.md",
      "status": "pending",
      "title": "战火"
    },
    {
      "index": 435,
      "file": "Chapter 0435 牢狱.md",
      "status": "pending",
      "title": "牢狱"
    },
    {
      "index": 436,
      "file": "Chapter 0436 大张旗鼓.md",
      "status": "pending",
      "title": "大张旗鼓"
    },
    {
      "index": 437,
      "file": "Chapter 0437 贺礼.md",
      "status": "pending",
      "title": "贺礼"
    },
    {
      "index": 438,
      "file": "Chapter 0438 灭口.md",
      "status": "pending",
      "title": "灭口"
    },
    {
      "index": 439,
      "file": "Chapter 0439 在下陈棠！.md",
      "status": "pending",
      "title": "在下陈棠！"
    },
    {
      "index": 440,
      "file": "Chapter 0440 交锋.md",
      "status": "pending",
      "title": "交锋"
    },
    {
      "index": 441,
      "file": "Chapter 0441 引蛇出洞.md",
      "status": "pending",
      "title": "引蛇出洞"
    },
    {
      "index": 442,
      "file": "Chapter 0442 追杀.md",
      "status": "pending",
      "title": "追杀"
    },
    {
      "index": 443,
      "file": "Chapter 0443 玄天法坛.md",
      "status": "pending",
      "title": "玄天法坛"
    },
    {
      "index": 444,
      "file": "Chapter 0444 剑指玄天.md",
      "status": "pending",
      "title": "剑指玄天"
    },
    {
      "index": 445,
      "file": "Chapter 0445 入教.md",
      "status": "pending",
      "title": "入教"
    },
    {
      "index": 446,
      "file": "Chapter 0446 大开杀戒.md",
      "status": "pending",
      "title": "大开杀戒"
    },
    {
      "index": 447,
      "file": "Chapter 0447 送你们归天！.md",
      "status": "pending",
      "title": "送你们归天！"
    },
    {
      "index": 448,
      "file": "Chapter 0448 凶多吉少.md",
      "status": "pending",
      "title": "凶多吉少"
    },
    {
      "index": 449,
      "file": "Chapter 0449 别来无恙.md",
      "status": "pending",
      "title": "别来无恙"
    },
    {
      "index": 450,
      "file": "Chapter 0450 恐怖一刀.md",
      "status": "pending",
      "title": "恐怖一刀"
    },
    {
      "index": 451,
      "file": "Chapter 0451 祸水东引.md",
      "status": "pending",
      "title": "祸水东引"
    },
    {
      "index": 452,
      "file": "Chapter 0452 血洗.md",
      "status": "pending",
      "title": "血洗"
    },
    {
      "index": 453,
      "file": "Chapter 0453 腥风血雨.md",
      "status": "pending",
      "title": "腥风血雨"
    },
    {
      "index": 454,
      "file": "Chapter 0454 魏公公.md",
      "status": "pending",
      "title": "魏公公"
    },
    {
      "index": 455,
      "file": "Chapter 0455 余太后.md",
      "status": "pending",
      "title": "余太后"
    },
    {
      "index": 456,
      "file": "Chapter 0456 剑阁出榜.md",
      "status": "pending",
      "title": "剑阁出榜"
    },
    {
      "index": 457,
      "file": "Chapter 0457 回家.md",
      "status": "pending",
      "title": "回家"
    },
    {
      "index": 458,
      "file": "Chapter 0458 虫蚁如潮.md",
      "status": "pending",
      "title": "虫蚁如潮"
    },
    {
      "index": 459,
      "file": "Chapter 0459 隐者踪迹.md",
      "status": "pending",
      "title": "隐者踪迹"
    },
    {
      "index": 460,
      "file": "Chapter 0460 顺手杀了.md",
      "status": "pending",
      "title": "顺手杀了"
    },
    {
      "index": 461,
      "file": "Chapter 0461 八石散.md",
      "status": "pending",
      "title": "八石散"
    },
    {
      "index": 462,
      "file": "Chapter 0462 霹雳堂.md",
      "status": "pending",
      "title": "霹雳堂"
    },
    {
      "index": 463,
      "file": "Chapter 0463 火器之威.md",
      "status": "pending",
      "title": "火器之威"
    },
    {
      "index": 464,
      "file": "Chapter 0464 人榜十一.md",
      "status": "pending",
      "title": "人榜十一"
    },
    {
      "index": 465,
      "file": "Chapter 0465 惨死.md",
      "status": "pending",
      "title": "惨死"
    },
    {
      "index": 466,
      "file": "Chapter 0466 遇袭.md",
      "status": "pending",
      "title": "遇袭"
    },
    {
      "index": 467,
      "file": "Chapter 0467 联手.md",
      "status": "pending",
      "title": "联手"
    },
    {
      "index": 468,
      "file": "Chapter 0468 来援.md",
      "status": "pending",
      "title": "来援"
    },
    {
      "index": 469,
      "file": "Chapter 0469 桃源谷.md",
      "status": "pending",
      "title": "桃源谷"
    },
    {
      "index": 470,
      "file": "Chapter 0470 飞鹰.md",
      "status": "pending",
      "title": "飞鹰"
    },
    {
      "index": 471,
      "file": "Chapter 0471 败退.md",
      "status": "pending",
      "title": "败退"
    },
    {
      "index": 472,
      "file": "Chapter 0472 铜头铁臂.md",
      "status": "pending",
      "title": "铜头铁臂"
    },
    {
      "index": 473,
      "file": "Chapter 0473 鬼影刀.md",
      "status": "pending",
      "title": "鬼影刀"
    },
    {
      "index": 474,
      "file": "Chapter 0474 少掌柜.md",
      "status": "pending",
      "title": "少掌柜"
    },
    {
      "index": 475,
      "file": "Chapter 0475 天罗网.md",
      "status": "pending",
      "title": "天罗网"
    },
    {
      "index": 476,
      "file": "Chapter 0476 杀出重围.md",
      "status": "pending",
      "title": "杀出重围"
    },
    {
      "index": 477,
      "file": "Chapter 0477 天马镖局.md",
      "status": "pending",
      "title": "天马镖局"
    },
    {
      "index": 478,
      "file": "Chapter 0478 瞒天过海.md",
      "status": "pending",
      "title": "瞒天过海"
    },
    {
      "index": 479,
      "file": "Chapter 0479 霹雳神掌.md",
      "status": "pending",
      "title": "霹雳神掌"
    },
    {
      "index": 480,
      "file": "Chapter 0480 掌心神雷.md",
      "status": "pending",
      "title": "掌心神雷"
    },
    {
      "index": 481,
      "file": "Chapter 0481 地榜之首.md",
      "status": "pending",
      "title": "地榜之首"
    },
    {
      "index": 482,
      "file": "Chapter 0482 一炷香.md",
      "status": "pending",
      "title": "一炷香"
    },
    {
      "index": 483,
      "file": "Chapter 0483 见面礼.md",
      "status": "pending",
      "title": "见面礼"
    },
    {
      "index": 484,
      "file": "Chapter 0484 江底追杀.md",
      "status": "pending",
      "title": "江底追杀"
    },
    {
      "index": 485,
      "file": "Chapter 0485 异变.md",
      "status": "pending",
      "title": "异变"
    },
    {
      "index": 486,
      "file": "Chapter 0486 斩天隐.md",
      "status": "pending",
      "title": "斩天隐"
    },
    {
      "index": 487,
      "file": "Chapter 0487 空丝垂钓.md",
      "status": "pending",
      "title": "空丝垂钓"
    },
    {
      "index": 488,
      "file": "Chapter 0488 放生.md",
      "status": "pending",
      "title": "放生"
    },
    {
      "index": 489,
      "file": "Chapter 0489 大宗师.md",
      "status": "pending",
      "title": "大宗师"
    },
    {
      "index": 490,
      "file": "Chapter 0490 北乾故人.md",
      "status": "pending",
      "title": "北乾故人"
    },
    {
      "index": 491,
      "file": "Chapter 0491 益州.md",
      "status": "pending",
      "title": "益州"
    },
    {
      "index": 492,
      "file": "Chapter 0492 来自仙子的复仇.md",
      "status": "pending",
      "title": "来自仙子的复仇"
    },
    {
      "index": 493,
      "file": "Chapter 0493 上乐金刚.md",
      "status": "pending",
      "title": "上乐金刚"
    },
    {
      "index": 494,
      "file": "Chapter 0494 大空寺怎么走？.md",
      "status": "pending",
      "title": "大空寺怎么走？"
    },
    {
      "index": 495,
      "file": "Chapter 0495 弑神.md",
      "status": "pending",
      "title": "弑神"
    },
    {
      "index": 496,
      "file": "Chapter 0496 梵音惑心.md",
      "status": "pending",
      "title": "梵音惑心"
    },
    {
      "index": 497,
      "file": "Chapter 0497 飞雪堂.md",
      "status": "pending",
      "title": "飞雪堂"
    },
    {
      "index": 498,
      "file": "Chapter 0498 神境拳法.md",
      "status": "pending",
      "title": "神境拳法"
    },
    {
      "index": 499,
      "file": "Chapter 0499 强势.md",
      "status": "pending",
      "title": "强势"
    },
    {
      "index": 500,
      "file": "Chapter 0500 破金身.md",
      "status": "pending",
      "title": "破金身"
    },
    {
      "index": 501,
      "file": "Chapter 0501 少年战神.md",
      "status": "pending",
      "title": "少年战神"
    },
    {
      "index": 502,
      "file": "Chapter 0502 分生死！.md",
      "status": "pending",
      "title": "分生死！"
    },
    {
      "index": 503,
      "file": "Chapter 0503 仗势欺人.md",
      "status": "pending",
      "title": "仗势欺人"
    },
    {
      "index": 504,
      "file": "Chapter 0504 怒目金刚.md",
      "status": "pending",
      "title": "怒目金刚"
    },
    {
      "index": 505,
      "file": "Chapter 0505 突破.md",
      "status": "pending",
      "title": "突破"
    },
    {
      "index": 506,
      "file": "Chapter 0506 不如求己.md",
      "status": "pending",
      "title": "不如求己"
    },
    {
      "index": 507,
      "file": "Chapter 0507 大巴山脉.md",
      "status": "pending",
      "title": "大巴山脉"
    },
    {
      "index": 508,
      "file": "Chapter 0508 送剑.md",
      "status": "pending",
      "title": "送剑"
    },
    {
      "index": 509,
      "file": "Chapter 0509 约定.md",
      "status": "pending",
      "title": "约定"
    },
    {
      "index": 510,
      "file": "Chapter 0510 翻脸无情.md",
      "status": "pending",
      "title": "翻脸无情"
    },
    {
      "index": 511,
      "file": "Chapter 0511 图谋.md",
      "status": "pending",
      "title": "图谋"
    },
    {
      "index": 512,
      "file": "Chapter 0512 剑宗罢手.md",
      "status": "pending",
      "title": "剑宗罢手"
    },
    {
      "index": 513,
      "file": "Chapter 0513 一触即发.md",
      "status": "pending",
      "title": "一触即发"
    },
    {
      "index": 514,
      "file": "Chapter 0514 勉强不来.md",
      "status": "pending",
      "title": "勉强不来"
    },
    {
      "index": 515,
      "file": "Chapter 0515 危机.md",
      "status": "pending",
      "title": "危机"
    },
    {
      "index": 516,
      "file": "Chapter 0516 凤箫仙子.md",
      "status": "pending",
      "title": "凤箫仙子"
    },
    {
      "index": 517,
      "file": "Chapter 0517 着凉.md",
      "status": "pending",
      "title": "着凉"
    },
    {
      "index": 518,
      "file": "Chapter 0518 月影凝霜.md",
      "status": "pending",
      "title": "月影凝霜"
    },
    {
      "index": 519,
      "file": "Chapter 0519 人有点蠢.md",
      "status": "pending",
      "title": "人有点蠢"
    },
    {
      "index": 520,
      "file": "Chapter 0520 大战.md",
      "status": "pending",
      "title": "大战"
    },
    {
      "index": 521,
      "file": "Chapter 0521 无一合之敌.md",
      "status": "pending",
      "title": "无一合之敌"
    },
    {
      "index": 522,
      "file": "Chapter 0522 还想逃？.md",
      "status": "pending",
      "title": "还想逃？"
    },
    {
      "index": 523,
      "file": "Chapter 0523 联手斩杀.md",
      "status": "pending",
      "title": "联手斩杀"
    },
    {
      "index": 524,
      "file": "Chapter 0524 我自学的.md",
      "status": "pending",
      "title": "我自学的"
    },
    {
      "index": 525,
      "file": "Chapter 0525 邀请.md",
      "status": "pending",
      "title": "邀请"
    },
    {
      "index": 526,
      "file": "Chapter 0526 取而代之.md",
      "status": "pending",
      "title": "取而代之"
    },
    {
      "index": 527,
      "file": "Chapter 0527 刺杀目标.md",
      "status": "pending",
      "title": "刺杀目标"
    },
    {
      "index": 528,
      "file": "Chapter 0528 江上霸主.md",
      "status": "pending",
      "title": "江上霸主"
    },
    {
      "index": 529,
      "file": "Chapter 0529 谁赢站谁.md",
      "status": "pending",
      "title": "谁赢站谁"
    },
    {
      "index": 530,
      "file": "Chapter 0530 武林盟.md",
      "status": "pending",
      "title": "武林盟"
    },
    {
      "index": 531,
      "file": "Chapter 0531 造势.md",
      "status": "pending",
      "title": "造势"
    },
    {
      "index": 532,
      "file": "Chapter 0532 谁在骂我？.md",
      "status": "pending",
      "title": "谁在骂我？"
    },
    {
      "index": 533,
      "file": "Chapter 0533 杀心.md",
      "status": "pending",
      "title": "杀心"
    },
    {
      "index": 534,
      "file": "Chapter 0534 你急什么？.md",
      "status": "pending",
      "title": "你急什么？"
    },
    {
      "index": 535,
      "file": "Chapter 0535 我还没死.md",
      "status": "pending",
      "title": "我还没死"
    },
    {
      "index": 536,
      "file": "Chapter 0536 双榜之首.md",
      "status": "pending",
      "title": "双榜之首"
    },
    {
      "index": 537,
      "file": "Chapter 0537 万古归来.md",
      "status": "pending",
      "title": "万古归来"
    },
    {
      "index": 538,
      "file": "Chapter 0538 通灵.md",
      "status": "pending",
      "title": "通灵"
    },
    {
      "index": 539,
      "file": "Chapter 0539 自作多情.md",
      "status": "pending",
      "title": "自作多情"
    },
    {
      "index": 540,
      "file": "Chapter 0540 古怪刀法.md",
      "status": "pending",
      "title": "古怪刀法"
    },
    {
      "index": 541,
      "file": "Chapter 0541 到此为止.md",
      "status": "pending",
      "title": "到此为止"
    },
    {
      "index": 542,
      "file": "Chapter 0542 唯快不破.md",
      "status": "pending",
      "title": "唯快不破"
    },
    {
      "index": 543,
      "file": "Chapter 0543 燃木焚空.md",
      "status": "pending",
      "title": "燃木焚空"
    },
    {
      "index": 544,
      "file": "Chapter 0544 斩！.md",
      "status": "pending",
      "title": "斩！"
    },
    {
      "index": 545,
      "file": "Chapter 0545 剑拔弩张.md",
      "status": "pending",
      "title": "剑拔弩张"
    },
    {
      "index": 546,
      "file": "Chapter 0546 谁敢动她！.md",
      "status": "pending",
      "title": "谁敢动她！"
    },
    {
      "index": 547,
      "file": "Chapter 0547 盟主人选.md",
      "status": "pending",
      "title": "盟主人选"
    },
    {
      "index": 548,
      "file": "Chapter 0548 大势已去.md",
      "status": "pending",
      "title": "大势已去"
    },
    {
      "index": 549,
      "file": "Chapter 0549 桃花居士.md",
      "status": "pending",
      "title": "桃花居士"
    },
    {
      "index": 550,
      "file": "Chapter 0550 寒食大祭酒.md",
      "status": "pending",
      "title": "寒食大祭酒"
    },
    {
      "index": 551,
      "file": "Chapter 0551 局中局.md",
      "status": "pending",
      "title": "局中局"
    },
    {
      "index": 552,
      "file": "Chapter 0552 石破天惊.md",
      "status": "pending",
      "title": "石破天惊"
    },
    {
      "index": 553,
      "file": "Chapter 0553 贪天之功.md",
      "status": "pending",
      "title": "贪天之功"
    },
    {
      "index": 554,
      "file": "Chapter 0554 落幕.md",
      "status": "pending",
      "title": "落幕"
    },
    {
      "index": 555,
      "file": "Chapter 0555 返虚道人.md",
      "status": "pending",
      "title": "返虚道人"
    },
    {
      "index": 556,
      "file": "Chapter 0556 剑宗.md",
      "status": "pending",
      "title": "剑宗"
    },
    {
      "index": 557,
      "file": "Chapter 0557 天地樊笼.md",
      "status": "pending",
      "title": "天地樊笼"
    },
    {
      "index": 558,
      "file": "Chapter 0558 道宗.md",
      "status": "pending",
      "title": "道宗"
    },
    {
      "index": 559,
      "file": "Chapter 0559 武帝传道.md",
      "status": "pending",
      "title": "武帝传道"
    },
    {
      "index": 560,
      "file": "Chapter 0560 三品通脉（完）.md",
      "status": "pending",
      "title": "三品通脉（完）"
    },
    {
      "index": 561,
      "file": "Chapter 0561 送他上路.md",
      "status": "pending",
      "title": "送他上路"
    },
    {
      "index": 562,
      "file": "Chapter 0562 交易.md",
      "status": "pending",
      "title": "交易"
    },
    {
      "index": 563,
      "file": "Chapter 0563 一箭四雕.md",
      "status": "pending",
      "title": "一箭四雕"
    },
    {
      "index": 564,
      "file": "Chapter 0564 冷血无情.md",
      "status": "pending",
      "title": "冷血无情"
    },
    {
      "index": 565,
      "file": "Chapter 0565 机关算尽.md",
      "status": "pending",
      "title": "机关算尽"
    },
    {
      "index": 566,
      "file": "Chapter 0566 魔尊！.md",
      "status": "pending",
      "title": "魔尊！"
    },
    {
      "index": 567,
      "file": "Chapter 0567 梦魇之境.md",
      "status": "pending",
      "title": "梦魇之境"
    },
    {
      "index": 568,
      "file": "Chapter 0568 盖人杰也.md",
      "status": "pending",
      "title": "盖人杰也"
    },
    {
      "index": 569,
      "file": "Chapter 0569 他化自在宫.md",
      "status": "pending",
      "title": "他化自在宫"
    },
    {
      "index": 570,
      "file": "Chapter 0570 四魔.md",
      "status": "pending",
      "title": "四魔"
    },
    {
      "index": 571,
      "file": "Chapter 0571 人性本饿.md",
      "status": "pending",
      "title": "人性本饿"
    },
    {
      "index": 572,
      "file": "Chapter 0572 释魔经.md",
      "status": "pending",
      "title": "释魔经"
    },
    {
      "index": 573,
      "file": "Chapter 0573 重塑经脉.md",
      "status": "pending",
      "title": "重塑经脉"
    },
    {
      "index": 574,
      "file": "Chapter 0574 入浴.md",
      "status": "pending",
      "title": "入浴"
    },
    {
      "index": 575,
      "file": "Chapter 0575 私奔.md",
      "status": "pending",
      "title": "私奔"
    },
    {
      "index": 576,
      "file": "Chapter 0576 巡视诸国.md",
      "status": "pending",
      "title": "巡视诸国"
    },
    {
      "index": 577,
      "file": "Chapter 0577 丘兹舞女.md",
      "status": "pending",
      "title": "丘兹舞女"
    },
    {
      "index": 578,
      "file": "Chapter 0578 夜夜笙歌.md",
      "status": "pending",
      "title": "夜夜笙歌"
    },
    {
      "index": 579,
      "file": "Chapter 0579 龙阳之好.md",
      "status": "pending",
      "title": "龙阳之好"
    },
    {
      "index": 580,
      "file": "Chapter 0580 人皮壁画.md",
      "status": "pending",
      "title": "人皮壁画"
    },
    {
      "index": 581,
      "file": "Chapter 0581 人命值多少钱？.md",
      "status": "pending",
      "title": "人命值多少钱？"
    },
    {
      "index": 582,
      "file": "Chapter 0582 大开杀戒.md",
      "status": "pending",
      "title": "大开杀戒"
    },
    {
      "index": 583,
      "file": "Chapter 0583 下马威.md",
      "status": "pending",
      "title": "下马威"
    },
    {
      "index": 584,
      "file": "Chapter 0584 杀人偿命.md",
      "status": "pending",
      "title": "杀人偿命"
    },
    {
      "index": 585,
      "file": "Chapter 0585 竟然是你？.md",
      "status": "pending",
      "title": "竟然是你？"
    },
    {
      "index": 586,
      "file": "Chapter 0586 付之一炬.md",
      "status": "pending",
      "title": "付之一炬"
    },
    {
      "index": 587,
      "file": "Chapter 0587 金刚怒目.md",
      "status": "pending",
      "title": "金刚怒目"
    },
    {
      "index": 588,
      "file": "Chapter 0588 业火铸刀.md",
      "status": "pending",
      "title": "业火铸刀"
    },
    {
      "index": 589,
      "file": "Chapter 0589 拔罐.md",
      "status": "pending",
      "title": "拔罐"
    },
    {
      "index": 590,
      "file": "Chapter 0590 天马.md",
      "status": "pending",
      "title": "天马"
    },
    {
      "index": 591,
      "file": "Chapter 0591 没胆鬼.md",
      "status": "pending",
      "title": "没胆鬼"
    },
    {
      "index": 592,
      "file": "Chapter 0592 重逢.md",
      "status": "pending",
      "title": "重逢"
    },
    {
      "index": 593,
      "file": "Chapter 0593 刁难.md",
      "status": "pending",
      "title": "刁难"
    },
    {
      "index": 594,
      "file": "Chapter 0594 擒贼擒王.md",
      "status": "pending",
      "title": "擒贼擒王"
    },
    {
      "index": 595,
      "file": "Chapter 0595 铁伐烈.md",
      "status": "pending",
      "title": "铁伐烈"
    },
    {
      "index": 596,
      "file": "Chapter 0596 大夏正统.md",
      "status": "pending",
      "title": "大夏正统"
    },
    {
      "index": 597,
      "file": "Chapter 0597 陆夫人消息.md",
      "status": "pending",
      "title": "陆夫人消息"
    },
    {
      "index": 598,
      "file": "Chapter 0598 杀人为乐.md",
      "status": "pending",
      "title": "杀人为乐"
    },
    {
      "index": 599,
      "file": "Chapter 0599 龙雀刀.md",
      "status": "pending",
      "title": "龙雀刀"
    },
    {
      "index": 600,
      "file": "Chapter 0600 我想杀你！.md",
      "status": "pending",
      "title": "我想杀你！"
    },
    {
      "index": 601,
      "file": "Chapter 0601 死城.md",
      "status": "pending",
      "title": "死城"
    },
    {
      "index": 602,
      "file": "Chapter 0602 反击.md",
      "status": "pending",
      "title": "反击"
    },
    {
      "index": 603,
      "file": "Chapter 0603 等师尊.md",
      "status": "pending",
      "title": "等师尊"
    },
    {
      "index": 604,
      "file": "Chapter 0604 覆雨翻云.md",
      "status": "pending",
      "title": "覆雨翻云"
    },
    {
      "index": 605,
      "file": "Chapter 0605 莫得感情.md",
      "status": "pending",
      "title": "莫得感情"
    },
    {
      "index": 606,
      "file": "Chapter 0606 亏大了.md",
      "status": "pending",
      "title": "亏大了"
    },
    {
      "index": 607,
      "file": "Chapter 0607 乌孙国.md",
      "status": "pending",
      "title": "乌孙国"
    },
    {
      "index": 608,
      "file": "Chapter 0608 昆弥之争.md",
      "status": "pending",
      "title": "昆弥之争"
    },
    {
      "index": 609,
      "file": "Chapter 0609 疯老头.md",
      "status": "pending",
      "title": "疯老头"
    },
    {
      "index": 610,
      "file": "Chapter 0610 飞沙走石（三更求月票）.md",
      "status": "pending",
      "title": "飞沙走石（三更求月票）"
    },
    {
      "index": 611,
      "file": "Chapter 0611 士别三日.md",
      "status": "pending",
      "title": "士别三日"
    },
    {
      "index": 612,
      "file": "Chapter 0612 假途灭虢.md",
      "status": "pending",
      "title": "假途灭虢"
    },
    {
      "index": 613,
      "file": "Chapter 0613 故人海棠（三更）.md",
      "status": "pending",
      "title": "故人海棠（三更）"
    },
    {
      "index": 614,
      "file": "Chapter 0614 割地求和.md",
      "status": "pending",
      "title": "割地求和"
    },
    {
      "index": 615,
      "file": "Chapter 0615 秋后问斩.md",
      "status": "pending",
      "title": "秋后问斩"
    },
    {
      "index": 616,
      "file": "Chapter 0616 陷阱.md",
      "status": "pending",
      "title": "陷阱"
    },
    {
      "index": 617,
      "file": "Chapter 0617 瓮中之鳖.md",
      "status": "pending",
      "title": "瓮中之鳖"
    },
    {
      "index": 618,
      "file": "Chapter 0618 砍瓜切菜.md",
      "status": "pending",
      "title": "砍瓜切菜"
    },
    {
      "index": 619,
      "file": "Chapter 0619 唯手熟尔.md",
      "status": "pending",
      "title": "唯手熟尔"
    },
    {
      "index": 620,
      "file": "Chapter 0620 天山菩提.md",
      "status": "pending",
      "title": "天山菩提"
    },
    {
      "index": 621,
      "file": "Chapter 0621 粮草部队.md",
      "status": "pending",
      "title": "粮草部队"
    },
    {
      "index": 622,
      "file": "Chapter 0622 六国论（四更求月票）.md",
      "status": "pending",
      "title": "六国论（四更求月票）"
    },
    {
      "index": 623,
      "file": "Chapter 0623 蛮地六部.md",
      "status": "pending",
      "title": "蛮地六部"
    },
    {
      "index": 624,
      "file": "Chapter 0624 霸狮赤峰.md",
      "status": "pending",
      "title": "霸狮赤峰"
    },
    {
      "index": 625,
      "file": "Chapter 0625 大军压境.md",
      "status": "pending",
      "title": "大军压境"
    },
    {
      "index": 626,
      "file": "Chapter 0626 取上将首级.md",
      "status": "pending",
      "title": "取上将首级"
    },
    {
      "index": 627,
      "file": "Chapter 0627 破象阵.md",
      "status": "pending",
      "title": "破象阵"
    },
    {
      "index": 628,
      "file": "Chapter 0628 万人敌！.md",
      "status": "pending",
      "title": "万人敌！"
    },
    {
      "index": 629,
      "file": "Chapter 0629 宗师现身.md",
      "status": "pending",
      "title": "宗师现身"
    },
    {
      "index": 630,
      "file": "Chapter 0630 一刀绝顶.md",
      "status": "pending",
      "title": "一刀绝顶"
    },
    {
      "index": 631,
      "file": "Chapter 0631 战宗师.md",
      "status": "pending",
      "title": "战宗师"
    },
    {
      "index": 632,
      "file": "Chapter 0632 上天山.md",
      "status": "pending",
      "title": "上天山"
    },
    {
      "index": 633,
      "file": "Chapter 0633 尸体.md",
      "status": "pending",
      "title": "尸体"
    },
    {
      "index": 634,
      "file": "Chapter 0634 小金鹏.md",
      "status": "pending",
      "title": "小金鹏"
    },
    {
      "index": 635,
      "file": "Chapter 0635 联手（大章）.md",
      "status": "pending",
      "title": "联手（大章）"
    },
    {
      "index": 636,
      "file": "Chapter 0636 天山悟道.md",
      "status": "pending",
      "title": "天山悟道"
    },
    {
      "index": 637,
      "file": "Chapter 0637 夺舍.md",
      "status": "pending",
      "title": "夺舍"
    },
    {
      "index": 638,
      "file": "Chapter 0638 双极境.md",
      "status": "pending",
      "title": "双极境"
    },
    {
      "index": 639,
      "file": "Chapter 0639 败宗师.md",
      "status": "pending",
      "title": "败宗师"
    },
    {
      "index": 640,
      "file": "Chapter 0640 血菩提.md",
      "status": "pending",
      "title": "血菩提"
    },
    {
      "index": 641,
      "file": "Chapter 0641 逍遥游.md",
      "status": "pending",
      "title": "逍遥游"
    },
    {
      "index": 642,
      "file": "Chapter 0642 血痕.md",
      "status": "pending",
      "title": "血痕"
    },
    {
      "index": 643,
      "file": "Chapter 0643 看淡生死.md",
      "status": "pending",
      "title": "看淡生死"
    },
    {
      "index": 644,
      "file": "Chapter 0644 天地交感.md",
      "status": "pending",
      "title": "天地交感"
    },
    {
      "index": 645,
      "file": "Chapter 0645 黑云压城.md",
      "status": "pending",
      "title": "黑云压城"
    },
    {
      "index": 646,
      "file": "Chapter 0646 一线生机.md",
      "status": "pending",
      "title": "一线生机"
    },
    {
      "index": 647,
      "file": "Chapter 0647 呼雷豹逞凶.md",
      "status": "pending",
      "title": "呼雷豹逞凶"
    },
    {
      "index": 648,
      "file": "Chapter 0648 曙光.md",
      "status": "pending",
      "title": "曙光"
    },
    {
      "index": 649,
      "file": "Chapter 0649 一锤吐血.md",
      "status": "pending",
      "title": "一锤吐血"
    },
    {
      "index": 650,
      "file": "Chapter 0650 遛宗师.md",
      "status": "pending",
      "title": "遛宗师"
    },
    {
      "index": 651,
      "file": "Chapter 0651 惊雷.md",
      "status": "pending",
      "title": "惊雷"
    },
    {
      "index": 652,
      "file": "Chapter 0652 反噬.md",
      "status": "pending",
      "title": "反噬"
    },
    {
      "index": 653,
      "file": "Chapter 0653 天神！.md",
      "status": "pending",
      "title": "天神！"
    },
    {
      "index": 654,
      "file": "Chapter 0654 一溃千里.md",
      "status": "pending",
      "title": "一溃千里"
    },
    {
      "index": 655,
      "file": "Chapter 0655 故人消息.md",
      "status": "pending",
      "title": "故人消息"
    },
    {
      "index": 656,
      "file": "Chapter 0656 大礼（终）.md",
      "status": "pending",
      "title": "大礼（终）"
    },
    {
      "index": 657,
      "file": "Chapter 0657 归乡.md",
      "status": "pending",
      "title": "归乡"
    },
    {
      "index": 658,
      "file": "Chapter 0658 一枝梅.md",
      "status": "pending",
      "title": "一枝梅"
    },
    {
      "index": 659,
      "file": "Chapter 0659 异常.md",
      "status": "pending",
      "title": "异常"
    },
    {
      "index": 660,
      "file": "Chapter 0660 寒域神鹰.md",
      "status": "pending",
      "title": "寒域神鹰"
    },
    {
      "index": 661,
      "file": "Chapter 0661 一路同行.md",
      "status": "pending",
      "title": "一路同行"
    },
    {
      "index": 662,
      "file": "Chapter 0662 诀别.md",
      "status": "pending",
      "title": "诀别"
    },
    {
      "index": 663,
      "file": "Chapter 0663 笑声.md",
      "status": "pending",
      "title": "笑声"
    },
    {
      "index": 664,
      "file": "Chapter 0664 好久不见.md",
      "status": "pending",
      "title": "好久不见"
    },
    {
      "index": 665,
      "file": "Chapter 0665 大战.md",
      "status": "pending",
      "title": "大战"
    },
    {
      "index": 666,
      "file": "Chapter 0666 三大宗师.md",
      "status": "pending",
      "title": "三大宗师"
    },
    {
      "index": 667,
      "file": "Chapter 0667 全部镇压！.md",
      "status": "pending",
      "title": "全部镇压！"
    },
    {
      "index": 668,
      "file": "Chapter 0668 大胆！.md",
      "status": "pending",
      "title": "大胆！"
    },
    {
      "index": 669,
      "file": "Chapter 0669 斩王.md",
      "status": "pending",
      "title": "斩王"
    },
    {
      "index": 670,
      "file": "Chapter 0670 冰魄真经.md",
      "status": "pending",
      "title": "冰魄真经"
    },
    {
      "index": 671,
      "file": "Chapter 0671 鬼哭岭.md",
      "status": "pending",
      "title": "鬼哭岭"
    },
    {
      "index": 672,
      "file": "Chapter 0672 前朝旧部.md",
      "status": "pending",
      "title": "前朝旧部"
    },
    {
      "index": 673,
      "file": "Chapter 0673 龙虎霸主.md",
      "status": "pending",
      "title": "龙虎霸主"
    },
    {
      "index": 674,
      "file": "Chapter 0674 谁让你们走了？.md",
      "status": "pending",
      "title": "谁让你们走了？"
    },
    {
      "index": 675,
      "file": "Chapter 0675 你，听懂了吗.md",
      "status": "pending",
      "title": "你，听懂了吗"
    },
    {
      "index": 676,
      "file": "Chapter 0676 镇压！（三更求月票）.md",
      "status": "pending",
      "title": "镇压！（三更求月票）"
    },
    {
      "index": 677,
      "file": "Chapter 0677 选择.md",
      "status": "pending",
      "title": "选择"
    },
    {
      "index": 678,
      "file": "Chapter 0678 约见.md",
      "status": "pending",
      "title": "约见"
    },
    {
      "index": 679,
      "file": "Chapter 0679 交心.md",
      "status": "pending",
      "title": "交心"
    },
    {
      "index": 680,
      "file": "Chapter 0680 出山.md",
      "status": "pending",
      "title": "出山"
    },
    {
      "index": 681,
      "file": "Chapter 0681 一网打尽.md",
      "status": "pending",
      "title": "一网打尽"
    },
    {
      "index": 682,
      "file": "Chapter 0682 北伐.md",
      "status": "pending",
      "title": "北伐"
    },
    {
      "index": 683,
      "file": "Chapter 0683 以人作饵.md",
      "status": "pending",
      "title": "以人作饵"
    },
    {
      "index": 684,
      "file": "Chapter 0684 传艺.md",
      "status": "pending",
      "title": "传艺"
    },
    {
      "index": 685,
      "file": "Chapter 0685 朱门酒肉.md",
      "status": "pending",
      "title": "朱门酒肉"
    },
    {
      "index": 686,
      "file": "Chapter 0686 陈棠贺寿！.md",
      "status": "pending",
      "title": "陈棠贺寿！"
    },
    {
      "index": 687,
      "file": "Chapter 0687 斩蛟屠龙.md",
      "status": "pending",
      "title": "斩蛟屠龙"
    },
    {
      "index": 688,
      "file": "Chapter 0688 刀刀烈火.md",
      "status": "pending",
      "title": "刀刀烈火"
    },
    {
      "index": 689,
      "file": "Chapter 0689 活撕.md",
      "status": "pending",
      "title": "活撕"
    },
    {
      "index": 690,
      "file": "Chapter 0690 背后高人.md",
      "status": "pending",
      "title": "背后高人"
    },
    {
      "index": 691,
      "file": "Chapter 0691 金锤.md",
      "status": "pending",
      "title": "金锤"
    },
    {
      "index": 692,
      "file": "Chapter 0692 行刑（大章）.md",
      "status": "pending",
      "title": "行刑（大章）"
    },
    {
      "index": 693,
      "file": "Chapter 0693 生死之交.md",
      "status": "pending",
      "title": "生死之交"
    },
    {
      "index": 694,
      "file": "Chapter 0694 大闹乾京.md",
      "status": "pending",
      "title": "大闹乾京"
    },
    {
      "index": 695,
      "file": "Chapter 0695 大杀四方.md",
      "status": "pending",
      "title": "大杀四方"
    },
    {
      "index": 696,
      "file": "Chapter 0696 血溅五步.md",
      "status": "pending",
      "title": "血溅五步"
    },
    {
      "index": 697,
      "file": "Chapter 0697 有情有义小师弟.md",
      "status": "pending",
      "title": "有情有义小师弟"
    },
    {
      "index": 698,
      "file": "Chapter 0698 深入浅出.md",
      "status": "pending",
      "title": "深入浅出"
    },
    {
      "index": 699,
      "file": "Chapter 0699 明月有劫（终）.md",
      "status": "pending",
      "title": "明月有劫（终）"
    },
    {
      "index": 700,
      "file": "Chapter 0700 孝伯之死.md",
      "status": "pending",
      "title": "孝伯之死"
    },
    {
      "index": 701,
      "file": "Chapter 0701 旧都谈判.md",
      "status": "pending",
      "title": "旧都谈判"
    },
    {
      "index": 702,
      "file": "Chapter 0702 谁要见我？.md",
      "status": "pending",
      "title": "谁要见我？"
    },
    {
      "index": 703,
      "file": "Chapter 0703 反对无效.md",
      "status": "pending",
      "title": "反对无效"
    },
    {
      "index": 704,
      "file": "Chapter 0704 宗师！.md",
      "status": "pending",
      "title": "宗师！"
    },
    {
      "index": 705,
      "file": "Chapter 0705 一刀之威.md",
      "status": "pending",
      "title": "一刀之威"
    },
    {
      "index": 706,
      "file": "Chapter 0706 最强刺杀.md",
      "status": "pending",
      "title": "最强刺杀"
    },
    {
      "index": 707,
      "file": "Chapter 0707 东海之主.md",
      "status": "pending",
      "title": "东海之主"
    },
    {
      "index": 708,
      "file": "Chapter 0708 灭佛.md",
      "status": "pending",
      "title": "灭佛"
    },
    {
      "index": 709,
      "file": "Chapter 0709 自投罗网.md",
      "status": "pending",
      "title": "自投罗网"
    },
    {
      "index": 710,
      "file": "Chapter 0710 纳命来.md",
      "status": "pending",
      "title": "纳命来"
    },
    {
      "index": 711,
      "file": "Chapter 0711 北冥.md",
      "status": "pending",
      "title": "北冥"
    },
    {
      "index": 712,
      "file": "Chapter 0712 化境决战.md",
      "status": "pending",
      "title": "化境决战"
    },
    {
      "index": 713,
      "file": "Chapter 0713 八卦.md",
      "status": "pending",
      "title": "八卦"
    },
    {
      "index": 714,
      "file": "Chapter 0714 破阵！.md",
      "status": "pending",
      "title": "破阵！"
    },
    {
      "index": 715,
      "file": "Chapter 0715 道宗，武帝.md",
      "status": "pending",
      "title": "道宗，武帝"
    },
    {
      "index": 716,
      "file": "Chapter 0716 法相.md",
      "status": "pending",
      "title": "法相"
    },
    {
      "index": 717,
      "file": "Chapter 0717 绝境.md",
      "status": "pending",
      "title": "绝境"
    },
    {
      "index": 718,
      "file": "Chapter 0718 斩玄天.md",
      "status": "pending",
      "title": "斩玄天"
    },
    {
      "index": 719,
      "file": "Chapter 0719 双双殒命.md",
      "status": "pending",
      "title": "双双殒命"
    },
    {
      "index": 720,
      "file": "Chapter 0720 铸刀.md",
      "status": "pending",
      "title": "铸刀"
    },
    {
      "index": 721,
      "file": "Chapter 0721 不胜人间一场醉.md",
      "status": "pending",
      "title": "不胜人间一场醉"
    },
    {
      "index": 722,
      "file": "Chapter 0722 魂归故里.md",
      "status": "pending",
      "title": "魂归故里"
    },
    {
      "index": 723,
      "file": "Chapter 0723 发兵北乾.md",
      "status": "pending",
      "title": "发兵北乾"
    },
    {
      "index": 724,
      "file": "Chapter 0724 刀意对决.md",
      "status": "pending",
      "title": "刀意对决"
    },
    {
      "index": 725,
      "file": "Chapter 0725 天罚.md",
      "status": "pending",
      "title": "天罚"
    },
    {
      "index": 726,
      "file": "Chapter 0726 天下大乱.md",
      "status": "pending",
      "title": "天下大乱"
    },
    {
      "index": 727,
      "file": "Chapter 0727 一个死人.md",
      "status": "pending",
      "title": "一个死人"
    },
    {
      "index": 728,
      "file": "Chapter 0728 归期夜雨.md",
      "status": "pending",
      "title": "归期夜雨"
    },
    {
      "index": 729,
      "file": "Chapter 0729 情之一字.md",
      "status": "pending",
      "title": "情之一字"
    },
    {
      "index": 730,
      "file": "Chapter 0730 却话巴山夜雨时.md",
      "status": "pending",
      "title": "却话巴山夜雨时"
    },
    {
      "index": 731,
      "file": "Chapter 0731 凶名赫赫.md",
      "status": "pending",
      "title": "凶名赫赫"
    },
    {
      "index": 732,
      "file": "Chapter 0732 斩阴魔.md",
      "status": "pending",
      "title": "斩阴魔"
    },
    {
      "index": 733,
      "file": "Chapter 0733 大乘教.md",
      "status": "pending",
      "title": "大乘教"
    },
    {
      "index": 734,
      "file": "Chapter 0734 魔音.md",
      "status": "pending",
      "title": "魔音"
    },
    {
      "index": 735,
      "file": "Chapter 0735 大乘覆灭（三更）.md",
      "status": "pending",
      "title": "大乘覆灭（三更）"
    },
    {
      "index": 736,
      "file": "Chapter 0736 联姻（四更）.md",
      "status": "pending",
      "title": "联姻（四更）"
    },
    {
      "index": 737,
      "file": "Chapter 0737 炮烙之刑（五更求月票）.md",
      "status": "pending",
      "title": "炮烙之刑（五更求月票）"
    },
    {
      "index": 738,
      "file": "Chapter 0738 君临大夏（六更）.md",
      "status": "pending",
      "title": "君临大夏（六更）"
    },
    {
      "index": 739,
      "file": "Chapter 0739 南夏覆灭.md",
      "status": "pending",
      "title": "南夏覆灭"
    },
    {
      "index": 740,
      "file": "Chapter 0740 宋武起义.md",
      "status": "pending",
      "title": "宋武起义"
    },
    {
      "index": 741,
      "file": "Chapter 0741 再斩二人.md",
      "status": "pending",
      "title": "再斩二人"
    },
    {
      "index": 742,
      "file": "Chapter 0742 昆仑山见.md",
      "status": "pending",
      "title": "昆仑山见"
    },
    {
      "index": 743,
      "file": "Chapter 0743 离别.md",
      "status": "pending",
      "title": "离别"
    },
    {
      "index": 744,
      "file": "Chapter 0744 长生.md",
      "status": "pending",
      "title": "长生"
    },
    {
      "index": 745,
      "file": "Chapter 0745 决战.md",
      "status": "pending",
      "title": "决战"
    },
    {
      "index": 746,
      "file": "Chapter 0746 法宝.md",
      "status": "pending",
      "title": "法宝"
    },
    {
      "index": 747,
      "file": "Chapter 0747 道法自然.md",
      "status": "pending",
      "title": "道法自然"
    },
    {
      "index": 748,
      "file": "Chapter 0748 破碎虚空.md",
      "status": "pending",
      "title": "破碎虚空"
    },
    {
      "index": 749,
      "file": "Chapter 0749 万古刀宗（大结局）.md",
      "status": "pending",
      "title": "万古刀宗（大结局）"
    },
    {
      "index": 750,
      "file": "Chapter 0750 完本感言.md",
      "status": "pending",
      "title": "完本感言"
    },
    {
      "index": 751,
      "file": "Chapter 0751 完本感言.md",
      "status": "pending",
      "title": "完本感言"
    },
    {
      "index": 752,
      "file": "Chapter 0752 番外 《桃李章》.md",
      "status": "pending",
      "title": "番外 《桃李章》"
    },
    {
      "index": 753,
      "file": "Chapter 0753 番外 《桃李章》.md",
      "status": "pending",
      "title": "番外 《桃李章》"
    }
  ]
}